{
  "seed": "приёмка маркированного товара",
  "slug": "при-мка-маркированного-товара",
  "category": "intent",
  "cluster": "markirovka",
  "fetchedAt": "2026-07-20T14:33:11.046Z",
  "count": 29,
  "phrases": [
    {
      "phrase": "приемка маркированного товара",
      "count": 1498
    },
    {
      "phrase": "приемка маркированного товара в 1с",
      "count": 253
    },
    {
      "phrase": "приемка маркированного товара в эдо",
      "count": 84
    },
    {
      "phrase": "процесс приемки маркированного товара",
      "count": 75
    },
    {
      "phrase": "приемка маркированного товара в честном знаке",
      "count": 65
    },
    {
      "phrase": "приемка маркированного товара в 1с ут",
      "count": 54
    },
    {
      "phrase": "работа с маркируемым товаром по процессу приемка",
      "count": 48
    },
    {
      "phrase": "унф приемка маркированного товара",
      "count": 44
    },
    {
      "phrase": "приемка маркированного товара в эвотор",
      "count": 44
    },
    {
      "phrase": "приемка маркированного товара в 1с унф",
      "count": 37
    },
    {
      "phrase": "приемка маркированного товара в 1с розница",
      "count": 36
    },
    {
      "phrase": "приемка маркированного товара в сбис",
      "count": 31
    },
    {
      "phrase": "сроки приемки маркированного товара",
      "count": 30
    },
    {
      "phrase": "маркированный товар в 1с отгрузка и приемка",
      "count": 26
    },
    {
      "phrase": "порядок приемки маркируемой товара",
      "count": 21
    },
    {
      "phrase": "правила приемки маркированного товара",
      "count": 19
    },
    {
      "phrase": "инструкция по приемке маркированного товара",
      "count": 18
    },
    {
      "phrase": "частичная приемка маркированного товара",
      "count": 17
    },
    {
      "phrase": "клеверенс приемка маркированного товара",
      "count": 17
    },
    {
      "phrase": "приемка маркированного товара на кассе эвотор",
      "count": 17
    },
    {
      "phrase": "ошибки при приемке маркированного товара",
      "count": 16
    },
    {
      "phrase": "приемка маркированного товара в еис",
      "count": 16
    },
    {
      "phrase": "приемка маркированного товара в мой склад",
      "count": 14
    },
    {
      "phrase": "как происходит приемка маркированного товара",
      "count": 13
    },
    {
      "phrase": "как осуществляется приемка маркированных товаров",
      "count": 13
    },
    {
      "phrase": "склад 15 приемка маркированного товара",
      "count": 11
    },
    {
      "phrase": "приемка маркированного товара в 1с бухгалтерия",
      "count": 10
    },
    {
      "phrase": "datamobile приемка маркированного товара",
      "count": 8
    },
    {
      "phrase": "приемка маркированного товара на ордерный склад",
      "count": 4
    }
  ]
}
