{
  "seed": "Штрих-М",
  "slug": "штрих-м",
  "category": "entity",
  "cluster": "kkt",
  "fetchedAt": "2026-07-20T06:39:53.249Z",
  "count": 1304,
  "phrases": [
    {
      "phrase": "штрих м",
      "count": 33768
    },
    {
      "phrase": "штрих м драйвер",
      "count": 3637
    },
    {
      "phrase": "касса штрих м",
      "count": 3330
    },
    {
      "phrase": "тахограф штрих м",
      "count": 2947
    },
    {
      "phrase": "ккт штрих м",
      "count": 2635
    },
    {
      "phrase": "штрих м 01ф",
      "count": 2338
    },
    {
      "phrase": "штрих м кассир",
      "count": 1899
    },
    {
      "phrase": "весы штрих м",
      "count": 1829
    },
    {
      "phrase": "м м штрих коды",
      "count": 1792
    },
    {
      "phrase": "штрих м ошибка",
      "count": 1717
    },
    {
      "phrase": "штрих м чек",
      "count": 1581
    },
    {
      "phrase": "штрих м пиот",
      "count": 1500
    },
    {
      "phrase": "штрих м 5",
      "count": 1459
    },
    {
      "phrase": "штрих м прошивка",
      "count": 1451
    },
    {
      "phrase": "штрих м настройки",
      "count": 1329
    },
    {
      "phrase": "штрих м драйвер ккт",
      "count": 1174
    },
    {
      "phrase": "штрих м торговое",
      "count": 1125
    },
    {
      "phrase": "1с штрих м",
      "count": 1094
    },
    {
      "phrase": "штрих м скачать",
      "count": 1043
    },
    {
      "phrase": "штрих м кассир 5",
      "count": 1024
    },
    {
      "phrase": "штрих принт м",
      "count": 921
    },
    {
      "phrase": "штрих м 02ф",
      "count": 807
    },
    {
      "phrase": "тс пиот штрих м",
      "count": 801
    },
    {
      "phrase": "аппарат штрих м",
      "count": 736
    },
    {
      "phrase": "штрих м офд",
      "count": 697
    },
    {
      "phrase": "карта штрих м",
      "count": 689
    },
    {
      "phrase": "кассовый аппарат штрих м",
      "count": 671
    },
    {
      "phrase": "штрих м 15",
      "count": 663
    },
    {
      "phrase": "штрих м тест",
      "count": 655
    },
    {
      "phrase": "штрих м инструкция",
      "count": 641
    },
    {
      "phrase": "тест драйвер штрих м",
      "count": 595
    },
    {
      "phrase": "весы штрих принт м",
      "count": 583
    },
    {
      "phrase": "штрих м 01",
      "count": 583
    },
    {
      "phrase": "штрих м подключение",
      "count": 578
    },
    {
      "phrase": "штрих м предприятие",
      "count": 576
    },
    {
      "phrase": "штрих м карты тахографа",
      "count": 557
    },
    {
      "phrase": "штрих м 1",
      "count": 549
    },
    {
      "phrase": "штрих м фн",
      "count": 548
    },
    {
      "phrase": "штрих м 2",
      "count": 542
    },
    {
      "phrase": "ккм штрих м",
      "count": 541
    },
    {
      "phrase": "штрих м ф",
      "count": 522
    },
    {
      "phrase": "торговый баланс штрих м",
      "count": 510
    },
    {
      "phrase": "штрих м торговое предприятие",
      "count": 510
    },
    {
      "phrase": "штрих принт м 15",
      "count": 496
    },
    {
      "phrase": "штрих м 7",
      "count": 493
    },
    {
      "phrase": "скачать драйвер штрих м",
      "count": 453
    },
    {
      "phrase": "штрих м лицензия",
      "count": 449
    },
    {
      "phrase": "штрих м 15 2.5",
      "count": 447
    },
    {
      "phrase": "штрих м этикетки",
      "count": 445
    },
    {
      "phrase": "штрих м купить",
      "count": 443
    },
    {
      "phrase": "сайт штрих м",
      "count": 439
    },
    {
      "phrase": "штрих м обновления",
      "count": 434
    },
    {
      "phrase": "эмма м штрих",
      "count": 420
    },
    {
      "phrase": "эмма м штрих коды",
      "count": 418
    },
    {
      "phrase": "штрих м официальный",
      "count": 415
    },
    {
      "phrase": "фискальный штрих м",
      "count": 407
    },
    {
      "phrase": "штрих принт м 15 2.5",
      "count": 404
    },
    {
      "phrase": "подключить штрих м",
      "count": 395
    },
    {
      "phrase": "штрих м отчеты",
      "count": 391
    },
    {
      "phrase": "штрих м официальный сайт",
      "count": 386
    },
    {
      "phrase": "весы штрих м 15",
      "count": 378
    },
    {
      "phrase": "штрих м ффд",
      "count": 361
    },
    {
      "phrase": "штрих м настроить",
      "count": 348
    },
    {
      "phrase": "штрих м лента",
      "count": 339
    },
    {
      "phrase": "программа штрих м",
      "count": 338
    },
    {
      "phrase": "штрих м время",
      "count": 338
    },
    {
      "phrase": "штрих м производитель",
      "count": 333
    },
    {
      "phrase": "штрих м коррекция чека",
      "count": 329
    },
    {
      "phrase": "штрих м предприятие 7",
      "count": 329
    },
    {
      "phrase": "штрих м торговое предприятие 7",
      "count": 318
    },
    {
      "phrase": "штрих м весы с печатью",
      "count": 317
    },
    {
      "phrase": "штрих м установить",
      "count": 314
    },
    {
      "phrase": "штрих м печать этикеток",
      "count": 312
    },
    {
      "phrase": "штрих м 01 ф",
      "count": 309
    },
    {
      "phrase": "штрих м 3",
      "count": 307
    },
    {
      "phrase": "штрих м 01ф пиот",
      "count": 305
    },
    {
      "phrase": "весы штрих принт м 15",
      "count": 302
    },
    {
      "phrase": "работа штрих м",
      "count": 301
    },
    {
      "phrase": "штрих м весы с печатью этикеток",
      "count": 299
    },
    {
      "phrase": "ккт штрих м 01ф",
      "count": 291
    },
    {
      "phrase": "установка штрих м",
      "count": 291
    },
    {
      "phrase": "тс пилот штрих м",
      "count": 283
    },
    {
      "phrase": "штрих м онлайн",
      "count": 277
    },
    {
      "phrase": "весы штрих м 15 2.5",
      "count": 277
    },
    {
      "phrase": "штрих м работать",
      "count": 271
    },
    {
      "phrase": "подписка штрих м",
      "count": 260
    },
    {
      "phrase": "ффд 1.2 штрих м",
      "count": 258
    },
    {
      "phrase": "ошибки кассы штрих м",
      "count": 254
    },
    {
      "phrase": "штрих м таблицы",
      "count": 253
    },
    {
      "phrase": "штрих м poscenter",
      "count": 252
    },
    {
      "phrase": "штрих м дата",
      "count": 249
    },
    {
      "phrase": "штрих м драйвер 1с",
      "count": 248
    },
    {
      "phrase": "штрих м 01ф прошивка",
      "count": 244
    },
    {
      "phrase": "штрих м сканер",
      "count": 242
    },
    {
      "phrase": "регистратор штрих м",
      "count": 242
    },
    {
      "phrase": "весы штрих принт м 15 2.5",
      "count": 240
    },
    {
      "phrase": "штрих м электронно",
      "count": 238
    },
    {
      "phrase": "rndis штрих м",
      "count": 235
    },
    {
      "phrase": "тахограф штрих м инструкция",
      "count": 226
    },
    {
      "phrase": "штрих м 01ф драйвер",
      "count": 218
    },
    {
      "phrase": "тест драйвера ккт штрих м",
      "count": 215
    },
    {
      "phrase": "штрих м 5.17",
      "count": 213
    },
    {
      "phrase": "штрих м лайт",
      "count": 209
    },
    {
      "phrase": "штрих м передача в офд",
      "count": 207
    },
    {
      "phrase": "пиот настройка штрих м",
      "count": 206
    },
    {
      "phrase": "штрих м команды",
      "count": 205
    },
    {
      "phrase": "штрих м замена фн",
      "count": 204
    },
    {
      "phrase": "устройство штрих м",
      "count": 202
    },
    {
      "phrase": "штрих м номер",
      "count": 201
    },
    {
      "phrase": "штрих м 02",
      "count": 201
    },
    {
      "phrase": "штрих м ккт скачать",
      "count": 198
    },
    {
      "phrase": "штрих м порт",
      "count": 198
    },
    {
      "phrase": "штрих м ящик",
      "count": 197
    },
    {
      "phrase": "штрих м возврат",
      "count": 197
    },
    {
      "phrase": "штрих м передача данных в офд",
      "count": 196
    },
    {
      "phrase": "обновить штрих м",
      "count": 192
    },
    {
      "phrase": "фискальный накопитель штрих м",
      "count": 192
    },
    {
      "phrase": "весы электронные штрих м",
      "count": 191
    },
    {
      "phrase": "штрих м 01ф тс пиот",
      "count": 190
    },
    {
      "phrase": "штрих м как вытащить карту",
      "count": 187
    },
    {
      "phrase": "ндс штрих м",
      "count": 187
    },
    {
      "phrase": "штрих м usb",
      "count": 186
    },
    {
      "phrase": "штрих м ккт с передачей данных",
      "count": 186
    },
    {
      "phrase": "денежный ящик штрих м",
      "count": 186
    },
    {
      "phrase": "элвес штрих м",
      "count": 184
    },
    {
      "phrase": "настройка штрих м кассир",
      "count": 181
    },
    {
      "phrase": "штрих м модуль",
      "count": 180
    },
    {
      "phrase": "штрих м цена",
      "count": 179
    },
    {
      "phrase": "штрих м драйвера 5.17",
      "count": 178
    },
    {
      "phrase": "маркировка штрих м",
      "count": 178
    },
    {
      "phrase": "штрих м карты водителя",
      "count": 178
    },
    {
      "phrase": "не видит штрих м",
      "count": 176
    },
    {
      "phrase": "розница штрих м",
      "count": 175
    },
    {
      "phrase": "касса штрих м 01ф",
      "count": 175
    },
    {
      "phrase": "фискальный регистратор штрих м",
      "count": 173
    },
    {
      "phrase": "штрих м центр",
      "count": 173
    },
    {
      "phrase": "штрих м ошибки е",
      "count": 173
    },
    {
      "phrase": "как пользоваться штрих м",
      "count": 172
    },
    {
      "phrase": "прошивки штрих м скачать",
      "count": 171
    },
    {
      "phrase": "штрих м торговля",
      "count": 171
    },
    {
      "phrase": "как вытащить тахограф штрих м",
      "count": 170
    },
    {
      "phrase": "карту тахограф штрих м карту водителя",
      "count": 168
    },
    {
      "phrase": "штрих м пиот прошивка",
      "count": 166
    },
    {
      "phrase": "штрих м включить",
      "count": 165
    },
    {
      "phrase": "штрих м сервис",
      "count": 162
    },
    {
      "phrase": "драйвер весов штрих м",
      "count": 161
    },
    {
      "phrase": "скачать драйвер ккт штрих м",
      "count": 160
    },
    {
      "phrase": "штрих м сканер штрих кода",
      "count": 159
    },
    {
      "phrase": "штрих м ккт 5.17",
      "count": 157
    },
    {
      "phrase": "штрих м базовая версия",
      "count": 157
    },
    {
      "phrase": "штрих м 02ф прошивка",
      "count": 153
    },
    {
      "phrase": "штрих м знак",
      "count": 153
    },
    {
      "phrase": "отрезчик штрих м",
      "count": 151
    },
    {
      "phrase": "оборудование штрих м",
      "count": 150
    },
    {
      "phrase": "штрих м 5.21",
      "count": 149
    },
    {
      "phrase": "штрих м фр к",
      "count": 147
    },
    {
      "phrase": "штрих м пробить чек",
      "count": 147
    },
    {
      "phrase": "как пользоваться тахографом штрих м",
      "count": 147
    },
    {
      "phrase": "штрих м com",
      "count": 144
    },
    {
      "phrase": "штрих м адрес",
      "count": 144
    },
    {
      "phrase": "штрих м ключ",
      "count": 141
    },
    {
      "phrase": "честный знак штрих м",
      "count": 139
    },
    {
      "phrase": "штрих м настройка офд",
      "count": 138
    },
    {
      "phrase": "штрих м кабель",
      "count": 137
    },
    {
      "phrase": "штрих м 5.2",
      "count": 136
    },
    {
      "phrase": "настройка кассы штрих м",
      "count": 134
    },
    {
      "phrase": "производитель кассы штрих м",
      "count": 134
    },
    {
      "phrase": "весы электронные штрих принт м",
      "count": 134
    },
    {
      "phrase": "штрих м инструкция для водителя",
      "count": 133
    },
    {
      "phrase": "штрих м не печатает",
      "count": 133
    },
    {
      "phrase": "тахограф штрих м инструкция для водителя",
      "count": 132
    },
    {
      "phrase": "штрих м посцентр",
      "count": 132
    },
    {
      "phrase": "штрих м 100",
      "count": 131
    },
    {
      "phrase": "штрих м драйвер ккт 5.17",
      "count": 130
    },
    {
      "phrase": "штрих м батарейка",
      "count": 129
    },
    {
      "phrase": "драйвер штрих м 5.21",
      "count": 129
    },
    {
      "phrase": "терминал штрих м",
      "count": 129
    },
    {
      "phrase": "штрих м обмен",
      "count": 127
    },
    {
      "phrase": "онлайн касса штрих м",
      "count": 126
    },
    {
      "phrase": "штрих м солюшенс",
      "count": 123
    },
    {
      "phrase": "штрих м версия прошивки",
      "count": 123
    },
    {
      "phrase": "драйвер штрих м версия",
      "count": 122
    },
    {
      "phrase": "штрих м 1с розница",
      "count": 121
    },
    {
      "phrase": "г штрих м штрих",
      "count": 121
    },
    {
      "phrase": "ошибки кассового аппарата штрих м",
      "count": 121
    },
    {
      "phrase": "штрих м документ",
      "count": 121
    },
    {
      "phrase": "фискализация штрих м",
      "count": 120
    },
    {
      "phrase": "протокол штрих м",
      "count": 119
    },
    {
      "phrase": "штрих м мастер",
      "count": 117
    },
    {
      "phrase": "штрих м 15 2 5",
      "count": 117
    },
    {
      "phrase": "штрих м настройка тс пиот",
      "count": 116
    },
    {
      "phrase": "штрих м прошивки ккт",
      "count": 116
    },
    {
      "phrase": "штрих м розничная торговля",
      "count": 115
    },
    {
      "phrase": "сервер штрих м",
      "count": 115
    },
    {
      "phrase": "прошивка кассы штрих м",
      "count": 114
    },
    {
      "phrase": "ккм солюшенс штрих м",
      "count": 114
    },
    {
      "phrase": "печать чеков штрих м",
      "count": 114
    },
    {
      "phrase": "штрих м печать чека",
      "count": 114
    },
    {
      "phrase": "штрих м кассир 5 настройки",
      "count": 113
    },
    {
      "phrase": "штрих м 5.25",
      "count": 113
    },
    {
      "phrase": "1с штрих м пиот",
      "count": 113
    },
    {
      "phrase": "1с предприятия штрих м",
      "count": 112
    },
    {
      "phrase": "настройка ккт штрих м",
      "count": 112
    },
    {
      "phrase": "штрих м атол",
      "count": 111
    },
    {
      "phrase": "как открыть штрих м",
      "count": 111
    },
    {
      "phrase": "штрих м драйвер чек коррекции",
      "count": 111
    },
    {
      "phrase": "штрих м настройка rndis",
      "count": 111
    },
    {
      "phrase": "1с касса штрих м",
      "count": 111
    },
    {
      "phrase": "штрих м распечатка",
      "count": 110
    },
    {
      "phrase": "штрих м пос",
      "count": 110
    },
    {
      "phrase": "принтер штрих м",
      "count": 109
    },
    {
      "phrase": "тест драйвер штрих м скачать",
      "count": 109
    },
    {
      "phrase": "система штрих м",
      "count": 109
    },
    {
      "phrase": "подключение ккт штрих м",
      "count": 109
    },
    {
      "phrase": "тахограф распечатка штрих м",
      "count": 107
    },
    {
      "phrase": "штрих м кассир скачать",
      "count": 107
    },
    {
      "phrase": "штрих м 01ф фн",
      "count": 107
    },
    {
      "phrase": "штрих м клавиатура",
      "count": 107
    },
    {
      "phrase": "штрих м тспиот",
      "count": 106
    },
    {
      "phrase": "штрих м видео",
      "count": 106
    },
    {
      "phrase": "пароль штрих м",
      "count": 106
    },
    {
      "phrase": "штрих м регистрация",
      "count": 106
    },
    {
      "phrase": "штрих м инструкция применения",
      "count": 105
    },
    {
      "phrase": "весы штрих м 2",
      "count": 104
    },
    {
      "phrase": "весы электронные штрих принт м 15 2.5",
      "count": 103
    },
    {
      "phrase": "настройка весов штрих м",
      "count": 103
    },
    {
      "phrase": "подключение тахографа штрих м",
      "count": 102
    },
    {
      "phrase": "штрих м нет связи",
      "count": 102
    },
    {
      "phrase": "штрих м 22",
      "count": 102
    },
    {
      "phrase": "штрих м новосибирск",
      "count": 101
    },
    {
      "phrase": "куплю штрих м 01ф",
      "count": 101
    },
    {
      "phrase": "ооо штрих м",
      "count": 101
    },
    {
      "phrase": "чек коррекции штрих м через драйвер",
      "count": 100
    },
    {
      "phrase": "чек коррекции на штрих м",
      "count": 100
    },
    {
      "phrase": "штрих м c",
      "count": 100
    },
    {
      "phrase": "штрих м лайт 01ф",
      "count": 100
    },
    {
      "phrase": "автоматизация штрих м",
      "count": 100
    },
    {
      "phrase": "штрих м мини",
      "count": 99
    },
    {
      "phrase": "весы штрих м 5",
      "count": 98
    },
    {
      "phrase": "компания штрих м",
      "count": 97
    },
    {
      "phrase": "кассовая лента штрих м",
      "count": 97
    },
    {
      "phrase": "штрих м мастер фискализации",
      "count": 97
    },
    {
      "phrase": "ip штрих м",
      "count": 96
    },
    {
      "phrase": "штрих м драйвер 5.25",
      "count": 96
    },
    {
      "phrase": "штрих м кассир пиот",
      "count": 96
    },
    {
      "phrase": "штрих м загрузчик",
      "count": 95
    },
    {
      "phrase": "штрих м как распечатать",
      "count": 95
    },
    {
      "phrase": "касса штрих м купить",
      "count": 92
    },
    {
      "phrase": "штрих м pos",
      "count": 92
    },
    {
      "phrase": "установить драйвер штрих м",
      "count": 90
    },
    {
      "phrase": "драйвер ккт штрих м 5.21",
      "count": 90
    },
    {
      "phrase": "штрих м руководство",
      "count": 90
    },
    {
      "phrase": "штрих м файл",
      "count": 89
    },
    {
      "phrase": "ошибки весов штрих м",
      "count": 89
    },
    {
      "phrase": "штрих м загрузки",
      "count": 89
    },
    {
      "phrase": "последний драйвер штрих м",
      "count": 89
    },
    {
      "phrase": "весы с печатью этикеток штрих принт м",
      "count": 88
    },
    {
      "phrase": "штрих м схема",
      "count": 87
    },
    {
      "phrase": "штрих м ремонт",
      "count": 86
    },
    {
      "phrase": "штрих м сервис обновления",
      "count": 86
    },
    {
      "phrase": "штрих м поддержка",
      "count": 86
    },
    {
      "phrase": "кассовый аппарат штрих м 01ф",
      "count": 86
    },
    {
      "phrase": "как вытащить карту из тахографа штрих м",
      "count": 86
    },
    {
      "phrase": "штрих м ошибки подключения",
      "count": 85
    },
    {
      "phrase": "штрих м кассир базовая",
      "count": 85
    },
    {
      "phrase": "кассовое по штрих м",
      "count": 84
    },
    {
      "phrase": "весы штрих м 15 2 5",
      "count": 84
    },
    {
      "phrase": "штрих м 5 скачать",
      "count": 84
    },
    {
      "phrase": "штрих м ккт драйвер 1с",
      "count": 83
    },
    {
      "phrase": "штрих м чек коррекции 1.2",
      "count": 83
    },
    {
      "phrase": "штрих м дата времени",
      "count": 82
    },
    {
      "phrase": "штрих м база",
      "count": 82
    },
    {
      "phrase": "штрих м драйвер ффд 1.2",
      "count": 82
    },
    {
      "phrase": "касса ккт штрих м",
      "count": 82
    },
    {
      "phrase": "тахограф штрих м инструкция по применению",
      "count": 81
    },
    {
      "phrase": "штрих м 4.15",
      "count": 81
    },
    {
      "phrase": "подписка на обновление штрих м",
      "count": 81
    },
    {
      "phrase": "штрих м торговое предприятие базовая",
      "count": 80
    },
    {
      "phrase": "штрих м сервис обновления фр",
      "count": 79
    },
    {
      "phrase": "штрих м прошивка 2026",
      "count": 79
    },
    {
      "phrase": "штрих м приложение",
      "count": 79
    },
    {
      "phrase": "штрих м 02 ф",
      "count": 79
    },
    {
      "phrase": "штрих м фото",
      "count": 78
    },
    {
      "phrase": "штрих принт м 15 2 5",
      "count": 78
    },
    {
      "phrase": "прошивка штрих м тс пиот",
      "count": 78
    },
    {
      "phrase": "весы штрих м 1с",
      "count": 78
    },
    {
      "phrase": "ккт штрих м 02ф",
      "count": 78
    },
    {
      "phrase": "код ошибок штрих м",
      "count": 76
    },
    {
      "phrase": "термоголовка штрих м",
      "count": 76
    },
    {
      "phrase": "аспд штрих м",
      "count": 76
    },
    {
      "phrase": "чек штрих м 01ф",
      "count": 76
    },
    {
      "phrase": "настройка подключения штрих м",
      "count": 75
    },
    {
      "phrase": "штрих м драйвер настройка",
      "count": 75
    },
    {
      "phrase": "перезагрузить штрих м",
      "count": 75
    },
    {
      "phrase": "штрих м кассир 5 базовый",
      "count": 74
    },
    {
      "phrase": "перерегистрация штрих м",
      "count": 74
    },
    {
      "phrase": "штрих м обновление прошивки",
      "count": 74
    },
    {
      "phrase": "не удалось подключить устройство штрих м",
      "count": 72
    },
    {
      "phrase": "штрих м кассир 5 скачать",
      "count": 72
    },
    {
      "phrase": "штрих м магазин",
      "count": 72
    },
    {
      "phrase": "чеки коррекции штрих м ффд 1.2",
      "count": 72
    },
    {
      "phrase": "штрих м элвес мф",
      "count": 71
    },
    {
      "phrase": "код маркировки штрих м",
      "count": 71
    },
    {
      "phrase": "штрих м интерфейс",
      "count": 71
    },
    {
      "phrase": "1с торговое предприятие штрих м",
      "count": 70
    },
    {
      "phrase": "штрих м 20",
      "count": 70
    },
    {
      "phrase": "1с штрих м кассир",
      "count": 70
    },
    {
      "phrase": "штрих м тп7",
      "count": 70
    },
    {
      "phrase": "возврат чеков штрих м",
      "count": 70
    },
    {
      "phrase": "штрих принт м драйвер",
      "count": 70
    },
    {
      "phrase": "чековая лента штрих м",
      "count": 69
    },
    {
      "phrase": "подключение кассы штрих м",
      "count": 69
    },
    {
      "phrase": "1с штрих м настройка",
      "count": 69
    },
    {
      "phrase": "штрих м возврат чека",
      "count": 68
    },
    {
      "phrase": "единая подписка штрих м",
      "count": 68
    },
    {
      "phrase": "не видит кассу штрих м",
      "count": 68
    },
    {
      "phrase": "штрих м ритейл",
      "count": 68
    },
    {
      "phrase": "схема тахографа штрих м",
      "count": 68
    },
    {
      "phrase": "штрих м 01ф ошибка",
      "count": 67
    },
    {
      "phrase": "км штрих м",
      "count": 66
    },
    {
      "phrase": "z отчет штрих м",
      "count": 66
    },
    {
      "phrase": "штрих м ошибка 113",
      "count": 66
    },
    {
      "phrase": "настройка штрих м 01ф",
      "count": 66
    },
    {
      "phrase": "штрих м торговое предприятие 7 базовая версия",
      "count": 66
    },
    {
      "phrase": "штрих принт м 15 2.5 д2и1",
      "count": 65
    },
    {
      "phrase": "настроить кассу штрих м",
      "count": 65
    },
    {
      "phrase": "ао штрих м",
      "count": 64
    },
    {
      "phrase": "ут штрих м",
      "count": 64
    },
    {
      "phrase": "штрих м 200",
      "count": 64
    },
    {
      "phrase": "подписка штрих м кассир",
      "count": 64
    },
    {
      "phrase": "штрих м как закрыть смену",
      "count": 64
    },
    {
      "phrase": "штрих м связь с офд",
      "count": 63
    },
    {
      "phrase": "штрих м техподдержка",
      "count": 63
    },
    {
      "phrase": "коррекция штрих м касса",
      "count": 63
    },
    {
      "phrase": "драйвер штрих м последняя версия",
      "count": 63
    },
    {
      "phrase": "калибровка штрих м",
      "count": 63
    },
    {
      "phrase": "схема подключения штрих м",
      "count": 63
    },
    {
      "phrase": "ошибка передачи данных штрих м",
      "count": 62
    },
    {
      "phrase": "штрих м 01ф замена фн",
      "count": 62
    },
    {
      "phrase": "штрих м ошибка при подключении устройства",
      "count": 62
    },
    {
      "phrase": "штрих м закрытия смены",
      "count": 62
    },
    {
      "phrase": "день штриха м",
      "count": 62
    },
    {
      "phrase": "штрих м 24",
      "count": 62
    },
    {
      "phrase": "тахограф штрих м схема подключения",
      "count": 62
    },
    {
      "phrase": "штрих м тахограф отдых",
      "count": 61
    },
    {
      "phrase": "штрих м кассир обновления",
      "count": 61
    },
    {
      "phrase": "обработки штрих м",
      "count": 61
    },
    {
      "phrase": "штрих м 01 драйвер",
      "count": 61
    },
    {
      "phrase": "штрих м обнуление",
      "count": 61
    },
    {
      "phrase": "штрих м скзи",
      "count": 60
    },
    {
      "phrase": "выгрузка штрих м",
      "count": 60
    },
    {
      "phrase": "штрих м драйвер 4.15",
      "count": 60
    },
    {
      "phrase": "штрих м достать карту",
      "count": 60
    },
    {
      "phrase": "штрих м ндс 22",
      "count": 60
    },
    {
      "phrase": "штрих м новосибирск официальный",
      "count": 60
    },
    {
      "phrase": "штрих м новосибирск официальный сайт",
      "count": 60
    },
    {
      "phrase": "штрих м новосибирск сайт",
      "count": 60
    },
    {
      "phrase": "штрих м сервисный",
      "count": 60
    },
    {
      "phrase": "штрих м как сделать возврат",
      "count": 59
    },
    {
      "phrase": "версия ккт штрих м",
      "count": 59
    },
    {
      "phrase": "касса штрих м ошибка е",
      "count": 59
    },
    {
      "phrase": "штрих м ошибка часов",
      "count": 59
    },
    {
      "phrase": "1с подключение штрих м",
      "count": 59
    },
    {
      "phrase": "штрих м лицензия ккт",
      "count": 58
    },
    {
      "phrase": "открытие смены штрих м",
      "count": 58
    },
    {
      "phrase": "штрих м 54 фз",
      "count": 58
    },
    {
      "phrase": "vcom штрих м",
      "count": 58
    },
    {
      "phrase": "весы штрих м инструкция",
      "count": 58
    },
    {
      "phrase": "касса штрих м пробить чек",
      "count": 58
    },
    {
      "phrase": "адаптер штрих м",
      "count": 58
    },
    {
      "phrase": "обновление лицензии штрих м",
      "count": 57
    },
    {
      "phrase": "прошить штрих м",
      "count": 57
    },
    {
      "phrase": "штрих м маркированный товар",
      "count": 57
    },
    {
      "phrase": "распайка для штрих м",
      "count": 57
    },
    {
      "phrase": "денежный ящик распайка штрих м",
      "count": 57
    },
    {
      "phrase": "регистратор штрих м штрих м 01ф",
      "count": 57
    },
    {
      "phrase": "как подключить кассу штрих м",
      "count": 56
    },
    {
      "phrase": "штрих м красная лампочка",
      "count": 56
    },
    {
      "phrase": "регистратор выбытия штрих м",
      "count": 56
    },
    {
      "phrase": "версия по штрих м",
      "count": 56
    },
    {
      "phrase": "настройка чеков штрих м",
      "count": 56
    },
    {
      "phrase": "штрих м распиновка",
      "count": 56
    },
    {
      "phrase": "штрих м меню",
      "count": 56
    },
    {
      "phrase": "тахограф штрих м купить",
      "count": 56
    },
    {
      "phrase": "штрих м петербург",
      "count": 56
    },
    {
      "phrase": "штрих м многоканальный протокол не поддерживается",
      "count": 55
    },
    {
      "phrase": "ккт штрих м 01",
      "count": 55
    },
    {
      "phrase": "кассовый аппарат штрих м лента",
      "count": 55
    },
    {
      "phrase": "штрих принт м 4.5",
      "count": 55
    },
    {
      "phrase": "штрих м инн",
      "count": 55
    },
    {
      "phrase": "штрих м смартпос",
      "count": 55
    },
    {
      "phrase": "1с штрих м 5.2",
      "count": 55
    },
    {
      "phrase": "штрих м прошивка т3",
      "count": 55
    },
    {
      "phrase": "штрих м 115",
      "count": 55
    },
    {
      "phrase": "штрих м егаис",
      "count": 55
    },
    {
      "phrase": "штрих м северо запад",
      "count": 55
    },
    {
      "phrase": "штрих м форум",
      "count": 54
    },
    {
      "phrase": "штрих м кассир базовая версия",
      "count": 54
    },
    {
      "phrase": "штрих принт м v 4.5",
      "count": 54
    },
    {
      "phrase": "штрих м клавиши",
      "count": 54
    },
    {
      "phrase": "штрих м прошивка тс пилот",
      "count": 54
    },
    {
      "phrase": "штрих м ушел",
      "count": 54
    },
    {
      "phrase": "штрих м minipos",
      "count": 54
    },
    {
      "phrase": "штрих м драйвер ккт 5.25",
      "count": 54
    },
    {
      "phrase": "штрих м тахограф коды",
      "count": 54
    },
    {
      "phrase": "штрих м 5 1с",
      "count": 54
    },
    {
      "phrase": "скачать эмма м штрих",
      "count": 53
    },
    {
      "phrase": "эмма м штрих коды скачать",
      "count": 53
    },
    {
      "phrase": "примеры штрих м",
      "count": 53
    },
    {
      "phrase": "vcom драйвер штрих м",
      "count": 53
    },
    {
      "phrase": "штрих м прошивка с3",
      "count": 53
    },
    {
      "phrase": "штрих м кассир 5 подписка",
      "count": 53
    },
    {
      "phrase": "касса штрих м 01",
      "count": 53
    },
    {
      "phrase": "настольные весы штрих м",
      "count": 53
    },
    {
      "phrase": "установка кассы штрих м",
      "count": 53
    },
    {
      "phrase": "штрих м настройка чека",
      "count": 52
    },
    {
      "phrase": "фискальный регистратор штрих м 01ф",
      "count": 52
    },
    {
      "phrase": "касса штрих м 02ф",
      "count": 52
    },
    {
      "phrase": "тест драйвера ккт штрих м скачать",
      "count": 52
    },
    {
      "phrase": "штрих м розничная торговля 5.2",
      "count": 52
    },
    {
      "phrase": "штрих м программное обеспечение",
      "count": 52
    },
    {
      "phrase": "драйвер для кассы штрих м",
      "count": 52
    },
    {
      "phrase": "штрих м теги",
      "count": 52
    },
    {
      "phrase": "тахограф штрих м ошибки",
      "count": 52
    },
    {
      "phrase": "работа тахографа штрих м",
      "count": 52
    },
    {
      "phrase": "штрих м реквизиты",
      "count": 52
    },
    {
      "phrase": "штрих м замена фискального накопителя",
      "count": 51
    },
    {
      "phrase": "ккт штрих м ф",
      "count": 51
    },
    {
      "phrase": "штрих м модели",
      "count": 51
    },
    {
      "phrase": "штрих м санкт петербург",
      "count": 51
    },
    {
      "phrase": "драйвер ккм штрих м",
      "count": 51
    },
    {
      "phrase": "штрих м гашение",
      "count": 50
    },
    {
      "phrase": "штрих м кассир 5 базовая версия",
      "count": 50
    },
    {
      "phrase": "штрих м распечатать чек",
      "count": 50
    },
    {
      "phrase": "торговый баланс штрих м драйвер",
      "count": 49
    },
    {
      "phrase": "штрих м драйвер фр",
      "count": 49
    },
    {
      "phrase": "штрих м 7.0",
      "count": 49
    },
    {
      "phrase": "штрих м 1.05",
      "count": 49
    },
    {
      "phrase": "ошибка 113 штрих м офд",
      "count": 49
    },
    {
      "phrase": "как извлечь карту из тахографа штрих м",
      "count": 49
    },
    {
      "phrase": "ошибка озу штрих м",
      "count": 49
    },
    {
      "phrase": "штрих м обновление ключей",
      "count": 49
    },
    {
      "phrase": "штрих м настройка печати",
      "count": 48
    },
    {
      "phrase": "штрих м 01ф скачать",
      "count": 48
    },
    {
      "phrase": "чек коррекции на кассе штрих м",
      "count": 48
    },
    {
      "phrase": "как распечатать тахограф штрих м",
      "count": 48
    },
    {
      "phrase": "касса штрих м инструкция",
      "count": 48
    },
    {
      "phrase": "штрих м драйвер 5",
      "count": 48
    },
    {
      "phrase": "шрифты штрих м",
      "count": 48
    },
    {
      "phrase": "штрих м ethernet",
      "count": 48
    },
    {
      "phrase": "штрих м слим",
      "count": 48
    },
    {
      "phrase": "штрих м кассир minipos",
      "count": 48
    },
    {
      "phrase": "как достать карту из тахографа штрих м",
      "count": 48
    },
    {
      "phrase": "сделать чек коррекции штрих м",
      "count": 48
    },
    {
      "phrase": "драйвер оборудования штрих м",
      "count": 48
    },
    {
      "phrase": "штрих м драйвер весов штрих принт",
      "count": 48
    },
    {
      "phrase": "штрих м ip адрес",
      "count": 48
    },
    {
      "phrase": "штрих м тп",
      "count": 47
    },
    {
      "phrase": "управление штрих м",
      "count": 47
    },
    {
      "phrase": "штрих м dhcp",
      "count": 47
    },
    {
      "phrase": "штрих м кассир 5 обновления",
      "count": 47
    },
    {
      "phrase": "песня штрих м",
      "count": 47
    },
    {
      "phrase": "плата штрих м",
      "count": 47
    },
    {
      "phrase": "штрих м кабинет",
      "count": 47
    },
    {
      "phrase": "распиновка тахографа штрих м",
      "count": 47
    },
    {
      "phrase": "штрих м ошибка 121",
      "count": 47
    },
    {
      "phrase": "штрих м личный",
      "count": 47
    },
    {
      "phrase": "штрих м 02ф драйвер",
      "count": 47
    },
    {
      "phrase": "штрих м прошивка с 3",
      "count": 46
    },
    {
      "phrase": "штрих м включение",
      "count": 46
    },
    {
      "phrase": "тахограф штрих м пишет",
      "count": 46
    },
    {
      "phrase": "центр отраслевых решений штрих м",
      "count": 46
    },
    {
      "phrase": "штрих м выгрузить данные",
      "count": 46
    },
    {
      "phrase": "штрих м обновление ключей проверки",
      "count": 46
    },
    {
      "phrase": "модернизация штрих м",
      "count": 46
    },
    {
      "phrase": "ккм штрих м 01ф",
      "count": 46
    },
    {
      "phrase": "тахограф штрих м лента",
      "count": 46
    },
    {
      "phrase": "штрих м личный кабинет",
      "count": 46
    },
    {
      "phrase": "сбис штрих м",
      "count": 46
    },
    {
      "phrase": "штрих м описание",
      "count": 45
    },
    {
      "phrase": "элвис штрих м",
      "count": 45
    },
    {
      "phrase": "штрих м номенклатура",
      "count": 45
    },
    {
      "phrase": "штрих м горит красным",
      "count": 45
    },
    {
      "phrase": "штрих м учет",
      "count": 45
    },
    {
      "phrase": "торговые весы штрих м",
      "count": 45
    },
    {
      "phrase": "открыть кассу штрих м",
      "count": 45
    },
    {
      "phrase": "штрих м ккт 4.15",
      "count": 45
    },
    {
      "phrase": "эмма м штрих текст",
      "count": 45
    },
    {
      "phrase": "пин код штрих м",
      "count": 44
    },
    {
      "phrase": "штрих м 01 ф прошивка",
      "count": 44
    },
    {
      "phrase": "ккм штрих м ошибка",
      "count": 44
    },
    {
      "phrase": "конфигурация штрих м",
      "count": 44
    },
    {
      "phrase": "неизвестная ошибка 113 штрих м",
      "count": 44
    },
    {
      "phrase": "штрих м пищит",
      "count": 44
    },
    {
      "phrase": "штрих м вставить ленту",
      "count": 44
    },
    {
      "phrase": "штрих м снять отчет",
      "count": 44
    },
    {
      "phrase": "штрих м инструкция по эксплуатации",
      "count": 44
    },
    {
      "phrase": "штрих принт м инструкция",
      "count": 44
    },
    {
      "phrase": "эмма м штрих коды текст",
      "count": 43
    },
    {
      "phrase": "штрих м 15 2.5 настройка",
      "count": 43
    },
    {
      "phrase": "ошибка штрих м 1",
      "count": 43
    },
    {
      "phrase": "штрих м мини пос",
      "count": 43
    },
    {
      "phrase": "штрих м некорректные параметры в команде",
      "count": 43
    },
    {
      "phrase": "штрих м 24 часа",
      "count": 43
    },
    {
      "phrase": "активация штрих м",
      "count": 43
    },
    {
      "phrase": "штрих м кассир 5 пиот",
      "count": 42
    },
    {
      "phrase": "весы настольные электронные штрих м",
      "count": 42
    },
    {
      "phrase": "ффд 1.05 штрих м",
      "count": 42
    },
    {
      "phrase": "штрих м торговое предприятие 5.2",
      "count": 42
    },
    {
      "phrase": "штрих принт м 15 2.5 настройка",
      "count": 42
    },
    {
      "phrase": "объект драйвера штрих м",
      "count": 42
    },
    {
      "phrase": "фр штрих м 01ф",
      "count": 42
    },
    {
      "phrase": "штрих м внесение",
      "count": 42
    },
    {
      "phrase": "штрих м посмотреть прошивку",
      "count": 42
    },
    {
      "phrase": "1с ут штрих м",
      "count": 42
    },
    {
      "phrase": "штрих м программа кассира",
      "count": 42
    },
    {
      "phrase": "ошибка печати штрих м",
      "count": 42
    },
    {
      "phrase": "штрих м ошибка 2",
      "count": 42
    },
    {
      "phrase": "актуальная прошивка штрих м",
      "count": 42
    },
    {
      "phrase": "группа штрих м",
      "count": 42
    },
    {
      "phrase": "штрих м инжиниринг",
      "count": 41
    },
    {
      "phrase": "песни эммы м штрихи",
      "count": 41
    },
    {
      "phrase": "песня эммы м штрих коды",
      "count": 41
    },
    {
      "phrase": "штрих м ввести код",
      "count": 41
    },
    {
      "phrase": "обновить кассу штрих м",
      "count": 41
    },
    {
      "phrase": "штрих м тахограф скзи",
      "count": 41
    },
    {
      "phrase": "штрих код м м карамель",
      "count": 41
    },
    {
      "phrase": "штрих м закрытие фн",
      "count": 41
    },
    {
      "phrase": "штрих м tcp",
      "count": 41
    },
    {
      "phrase": "штрих м торговое предприятие скачать",
      "count": 41
    },
    {
      "phrase": "штрих м касса 5",
      "count": 41
    },
    {
      "phrase": "кнопки на штрих м",
      "count": 41
    },
    {
      "phrase": "как выгрузить тахограф штрих м",
      "count": 41
    },
    {
      "phrase": "штрих м 01 ф драйвер",
      "count": 41
    },
    {
      "phrase": "касса элвес штрих м",
      "count": 41
    },
    {
      "phrase": "драйвер штрих м посцентр",
      "count": 41
    },
    {
      "phrase": "штрих м предприятие 5",
      "count": 40
    },
    {
      "phrase": "штрих м 4.15 скачать",
      "count": 40
    },
    {
      "phrase": "штрих м драйвер 4.15 скачать",
      "count": 40
    },
    {
      "phrase": "8 многоканальный протокол не поддерживается штрих м",
      "count": 40
    },
    {
      "phrase": "штрих м сбербанк",
      "count": 40
    },
    {
      "phrase": "штрих м как открыть смену",
      "count": 40
    },
    {
      "phrase": "продукция штрих м",
      "count": 40
    },
    {
      "phrase": "штрих м разобрать",
      "count": 40
    },
    {
      "phrase": "внешняя компонента штрих м",
      "count": 39
    },
    {
      "phrase": "штрих м 01ф лента",
      "count": 39
    },
    {
      "phrase": "штрих м сброс",
      "count": 39
    },
    {
      "phrase": "штрих м фр ф",
      "count": 39
    },
    {
      "phrase": "весы штрих принт м 4.5",
      "count": 39
    },
    {
      "phrase": "весы штрих принт м v 4.5",
      "count": 39
    },
    {
      "phrase": "штрих м птк",
      "count": 39
    },
    {
      "phrase": "штрих м номер кассы",
      "count": 38
    },
    {
      "phrase": "штрих м скидки",
      "count": 38
    },
    {
      "phrase": "штрих м ошибка 51",
      "count": 38
    },
    {
      "phrase": "штрих м закрыть фн",
      "count": 38
    },
    {
      "phrase": "штрих м инициализация sram",
      "count": 38
    },
    {
      "phrase": "штрих м драйвер прошивка",
      "count": 38
    },
    {
      "phrase": "штрих м установка драйвера",
      "count": 38
    },
    {
      "phrase": "штрих м изменения",
      "count": 38
    },
    {
      "phrase": "штрих м тахо",
      "count": 38
    },
    {
      "phrase": "штрих м телефон",
      "count": 38
    },
    {
      "phrase": "штрих м пей",
      "count": 38
    },
    {
      "phrase": "штрих м вай фай",
      "count": 38
    },
    {
      "phrase": "штрих м эвотор",
      "count": 38
    },
    {
      "phrase": "штрих принт м 15 2.5 д1и1",
      "count": 37
    },
    {
      "phrase": "как настроить тахограф штрих м",
      "count": 37
    },
    {
      "phrase": "connect time out штрих м",
      "count": 37
    },
    {
      "phrase": "штрих м нож",
      "count": 37
    },
    {
      "phrase": "ккт штрих м 01ф драйвер",
      "count": 37
    },
    {
      "phrase": "штрих м ошибка 5",
      "count": 37
    },
    {
      "phrase": "настройка связи штрих м",
      "count": 37
    },
    {
      "phrase": "весы штрих м инициализация sram",
      "count": 37
    },
    {
      "phrase": "как обновить штрих м кассира",
      "count": 37
    },
    {
      "phrase": "весы штрих м батарейка",
      "count": 37
    },
    {
      "phrase": "штрих м 2025",
      "count": 37
    },
    {
      "phrase": "подключение штрих м rndis",
      "count": 37
    },
    {
      "phrase": "лицензия штрих м 01ф",
      "count": 36
    },
    {
      "phrase": "штрих м стоимость",
      "count": 36
    },
    {
      "phrase": "штрих м возврат прихода",
      "count": 36
    },
    {
      "phrase": "ум штрих м",
      "count": 36
    },
    {
      "phrase": "как отключить тахограф штрих м",
      "count": 36
    },
    {
      "phrase": "штрих м снимите этикетку",
      "count": 36
    },
    {
      "phrase": "перерегистрация фн штрих м",
      "count": 36
    },
    {
      "phrase": "штрих м установить время",
      "count": 36
    },
    {
      "phrase": "как перезагрузить тахограф штрих м",
      "count": 36
    },
    {
      "phrase": "стеллаж штрих м",
      "count": 36
    },
    {
      "phrase": "весы штрих м 1",
      "count": 36
    },
    {
      "phrase": "штрих м моргает красным",
      "count": 36
    },
    {
      "phrase": "штрих м отключить отрезчик",
      "count": 35
    },
    {
      "phrase": "штрих м склад",
      "count": 35
    },
    {
      "phrase": "штрих м 02ф тс пиот",
      "count": 35
    },
    {
      "phrase": "закрытие фискального накопителя штрих м",
      "count": 35
    },
    {
      "phrase": "весы штрих принт м весы настройка",
      "count": 35
    },
    {
      "phrase": "штрих м характеристики",
      "count": 35
    },
    {
      "phrase": "штрих м расход",
      "count": 35
    },
    {
      "phrase": "штрих м как вставить карту",
      "count": 35
    },
    {
      "phrase": "штрих м замена батарейки",
      "count": 35
    },
    {
      "phrase": "штрих м таблица 17",
      "count": 35
    },
    {
      "phrase": "штрих м 01ф прошивка скачать",
      "count": 35
    },
    {
      "phrase": "штрих м 300",
      "count": 34
    },
    {
      "phrase": "настроить время штрих м",
      "count": 34
    },
    {
      "phrase": "штрих м аккумулятор",
      "count": 34
    },
    {
      "phrase": "инструкции штрих м кассир",
      "count": 34
    },
    {
      "phrase": "блок питания штрих м",
      "count": 34
    },
    {
      "phrase": "м штрих коды слушать",
      "count": 34
    },
    {
      "phrase": "м штрих слушать",
      "count": 34
    },
    {
      "phrase": "эмма м штрих коды слушать",
      "count": 34
    },
    {
      "phrase": "эмма м штрихами слушать",
      "count": 34
    },
    {
      "phrase": "штрих м выдает ошибку",
      "count": 34
    },
    {
      "phrase": "штрих м разъемы",
      "count": 34
    },
    {
      "phrase": "штрих м кассир 2",
      "count": 34
    },
    {
      "phrase": "1с штрих м кассир 5",
      "count": 34
    },
    {
      "phrase": "штрих м через usb",
      "count": 34
    },
    {
      "phrase": "ошибка 115 штрих м",
      "count": 34
    },
    {
      "phrase": "драйвера штрих м онлайн",
      "count": 34
    },
    {
      "phrase": "штрих м настройки таблиц",
      "count": 34
    },
    {
      "phrase": "штрих м разрешительный режим",
      "count": 34
    },
    {
      "phrase": "штрих м смартпос ф",
      "count": 34
    },
    {
      "phrase": "штрих м команда печать",
      "count": 34
    },
    {
      "phrase": "сайт штрих м тахографы",
      "count": 34
    },
    {
      "phrase": "весы штрих м пароль",
      "count": 33
    },
    {
      "phrase": "рмк штрих м",
      "count": 33
    },
    {
      "phrase": "штрих м прошивка 1.2",
      "count": 33
    },
    {
      "phrase": "обслуживание штрих м",
      "count": 33
    },
    {
      "phrase": "ошибка 54 штрих м",
      "count": 33
    },
    {
      "phrase": "работа кассы штрих м",
      "count": 33
    },
    {
      "phrase": "штрих м 5.0",
      "count": 33
    },
    {
      "phrase": "настроить весы штрих м",
      "count": 33
    },
    {
      "phrase": "обновить драйвер штрих м",
      "count": 33
    },
    {
      "phrase": "устройство модернизации штрих м",
      "count": 33
    },
    {
      "phrase": "штрих м не уходит офд",
      "count": 33
    },
    {
      "phrase": "штрих м режим работы",
      "count": 33
    },
    {
      "phrase": "штрих м е 103",
      "count": 32
    },
    {
      "phrase": "штрих м как вставить бумагу",
      "count": 32
    },
    {
      "phrase": "весы штрих м драйвер 1с",
      "count": 32
    },
    {
      "phrase": "штрих м принт ф1",
      "count": 32
    },
    {
      "phrase": "штрих м тп 7",
      "count": 32
    },
    {
      "phrase": "тахографы штрих м официальный",
      "count": 32
    },
    {
      "phrase": "штрих м тахографы официальный сайт",
      "count": 32
    },
    {
      "phrase": "штрих м центр загрузок",
      "count": 32
    },
    {
      "phrase": "пробитие чека штрих м",
      "count": 32
    },
    {
      "phrase": "штрих м таблица 1",
      "count": 32
    },
    {
      "phrase": "штрих м кассир купить",
      "count": 32
    },
    {
      "phrase": "как заправить штрих м",
      "count": 31
    },
    {
      "phrase": "штрих м не уходят чеки",
      "count": 31
    },
    {
      "phrase": "штрих м как вытащить карту водителя",
      "count": 31
    },
    {
      "phrase": "штрих м драйвер ккт чек драйвер",
      "count": 31
    },
    {
      "phrase": "штрих м ограничение ресурса фн",
      "count": 31
    },
    {
      "phrase": "кассовый штрих м инструкция",
      "count": 31
    },
    {
      "phrase": "штрих м ошибка 103",
      "count": 31
    },
    {
      "phrase": "штрих м ккм 1с",
      "count": 31
    },
    {
      "phrase": "мастер фискализации штрих м скачать",
      "count": 31
    },
    {
      "phrase": "штрих м 15 драйвер",
      "count": 31
    },
    {
      "phrase": "штрих м расшифровка",
      "count": 31
    },
    {
      "phrase": "версия ффд штрих м",
      "count": 31
    },
    {
      "phrase": "софт штрих м",
      "count": 31
    },
    {
      "phrase": "штрих м 5.18",
      "count": 31
    },
    {
      "phrase": "ошибка 247 штрих м",
      "count": 31
    },
    {
      "phrase": "штрих м как сделать возврат чека",
      "count": 31
    },
    {
      "phrase": "подключить штрих м к компьютеру",
      "count": 31
    },
    {
      "phrase": "штрих м другое состояние фн",
      "count": 31
    },
    {
      "phrase": "закрыть кассу штрих м",
      "count": 31
    },
    {
      "phrase": "штрих м последний чек",
      "count": 30
    },
    {
      "phrase": "как сделать распечатку с тахографа штрих м",
      "count": 30
    },
    {
      "phrase": "как обновить прошивку штрих м",
      "count": 30
    },
    {
      "phrase": "штрих м рндис",
      "count": 30
    },
    {
      "phrase": "перезагрузка штрих м",
      "count": 30
    },
    {
      "phrase": "штрих м 15 2.5 инструкция",
      "count": 30
    },
    {
      "phrase": "штрих принт м 15 2.5 инструкция",
      "count": 30
    },
    {
      "phrase": "обновление ккт штрих м",
      "count": 30
    },
    {
      "phrase": "штрих м порт занят другим приложением",
      "count": 30
    },
    {
      "phrase": "штрих м windows 10",
      "count": 30
    },
    {
      "phrase": "штрих м не отдает карту",
      "count": 30
    },
    {
      "phrase": "штрих м ошибка е 103",
      "count": 30
    },
    {
      "phrase": "лог штрих м",
      "count": 30
    },
    {
      "phrase": "штрих м 4.14",
      "count": 30
    },
    {
      "phrase": "сколько стоит штрих м",
      "count": 30
    },
    {
      "phrase": "штрих м замена фн перерегистрация",
      "count": 30
    },
    {
      "phrase": "штрих м проверка связи",
      "count": 30
    },
    {
      "phrase": "закрытие кассы штрих м",
      "count": 30
    },
    {
      "phrase": "штрих м ошибка 8",
      "count": 30
    },
    {
      "phrase": "1c штрих м",
      "count": 30
    },
    {
      "phrase": "весы штрих м снимите этикетку",
      "count": 30
    },
    {
      "phrase": "запчасти штрих м",
      "count": 29
    },
    {
      "phrase": "штрих м отменяет чек",
      "count": 29
    },
    {
      "phrase": "как подключить тахограф штрих м",
      "count": 29
    },
    {
      "phrase": "штрих м ошибка 94",
      "count": 29
    },
    {
      "phrase": "покажи тахограф штрих м",
      "count": 29
    },
    {
      "phrase": "как выгрузить данные с тахографа штрих м",
      "count": 29
    },
    {
      "phrase": "штрих м продолжение печати",
      "count": 29
    },
    {
      "phrase": "торговый дом штрих м",
      "count": 29
    },
    {
      "phrase": "1с штрих м торговое предприятие 7",
      "count": 29
    },
    {
      "phrase": "штрих м поменять ленту",
      "count": 29
    },
    {
      "phrase": "расшифровка штрих м тахограф",
      "count": 29
    },
    {
      "phrase": "штрих м подключение весов",
      "count": 29
    },
    {
      "phrase": "настройка тахографа штрих м",
      "count": 29
    },
    {
      "phrase": "кассовый аппарат штрих м инструкция",
      "count": 29
    },
    {
      "phrase": "установка ккт штрих м",
      "count": 29
    },
    {
      "phrase": "лицензия обновления фр штрих м",
      "count": 29
    },
    {
      "phrase": "лицензия штрих м сервис обновления фр",
      "count": 29
    },
    {
      "phrase": "гк штрих м",
      "count": 29
    },
    {
      "phrase": "окасса штрих м",
      "count": 29
    },
    {
      "phrase": "штрих м 5.20",
      "count": 29
    },
    {
      "phrase": "замена фн ккт штрих м",
      "count": 28
    },
    {
      "phrase": "штрих м поменять дату",
      "count": 28
    },
    {
      "phrase": "штрих м интеграция",
      "count": 28
    },
    {
      "phrase": "штрих м ошибка открытия смены",
      "count": 28
    },
    {
      "phrase": "буква м штрих м",
      "count": 28
    },
    {
      "phrase": "штрих м команда продолжения печати",
      "count": 28
    },
    {
      "phrase": "штрих м 01ф инструкция",
      "count": 28
    },
    {
      "phrase": "штрих м не печатать чеки",
      "count": 28
    },
    {
      "phrase": "замена фн штрих м инструкция",
      "count": 28
    },
    {
      "phrase": "штрих м настройка даты",
      "count": 28
    },
    {
      "phrase": "штрих м торговое предприятие 5",
      "count": 28
    },
    {
      "phrase": "штрих м настройка этикетки",
      "count": 28
    },
    {
      "phrase": "тахограф штрих м не отдает карту",
      "count": 28
    },
    {
      "phrase": "штрих м инвентаризации",
      "count": 28
    },
    {
      "phrase": "скачать драйвер весы штрих м",
      "count": 28
    },
    {
      "phrase": "тахограф штрих м как вытащить карту водителя",
      "count": 28
    },
    {
      "phrase": "ооо штрих м северо запад",
      "count": 27
    },
    {
      "phrase": "штрих м ru",
      "count": 27
    },
    {
      "phrase": "штрих м ценники",
      "count": 27
    },
    {
      "phrase": "тахограф штрих м как ввести код",
      "count": 27
    },
    {
      "phrase": "штрих м как поставить отдых",
      "count": 27
    },
    {
      "phrase": "чек коррекции штрих м как пробить",
      "count": 27
    },
    {
      "phrase": "не уходят чеки в офд штрих м",
      "count": 27
    },
    {
      "phrase": "весы штрих принт м 2мб",
      "count": 27
    },
    {
      "phrase": "штрих м кассовый аппарат дата",
      "count": 27
    },
    {
      "phrase": "1с штрих м торговое предприятие 5.2",
      "count": 27
    },
    {
      "phrase": "штрих м отрезка чека",
      "count": 27
    },
    {
      "phrase": "касса штрих м 01ф купить",
      "count": 27
    },
    {
      "phrase": "завис штрих м",
      "count": 26
    },
    {
      "phrase": "штрих м ошибка 153",
      "count": 26
    },
    {
      "phrase": "штрих м е 247",
      "count": 26
    },
    {
      "phrase": "штрих м контур",
      "count": 26
    },
    {
      "phrase": "установить драйвер ккт штрих м",
      "count": 26
    },
    {
      "phrase": "драйвер штрих м 5.20",
      "count": 26
    },
    {
      "phrase": "штрих м драйвер 5.18",
      "count": 26
    },
    {
      "phrase": "штрих м поменять время",
      "count": 26
    },
    {
      "phrase": "штрих м порт недоступен",
      "count": 26
    },
    {
      "phrase": "блок скзи штрих м",
      "count": 26
    },
    {
      "phrase": "штрих м ндс 5",
      "count": 26
    },
    {
      "phrase": "штрих м драйвер ндс",
      "count": 26
    },
    {
      "phrase": "штрих м драйвер отрезчик",
      "count": 26
    },
    {
      "phrase": "регистрация кассы штрих м",
      "count": 26
    },
    {
      "phrase": "тахограф штрих м как поставить на отдых",
      "count": 26
    },
    {
      "phrase": "офд не отвечает штрих м",
      "count": 26
    },
    {
      "phrase": "штрих м online",
      "count": 26
    },
    {
      "phrase": "штрих м кассир 5 инструкция",
      "count": 25
    },
    {
      "phrase": "штрих м закрылся",
      "count": 25
    },
    {
      "phrase": "купить ккт штрих м",
      "count": 25
    },
    {
      "phrase": "штрих м драйвер для тс пилот",
      "count": 25
    },
    {
      "phrase": "тахограф штрих м как вставить бумагу",
      "count": 25
    },
    {
      "phrase": "снять кассу штрих м",
      "count": 25
    },
    {
      "phrase": "штрих м usb драйвер",
      "count": 25
    },
    {
      "phrase": "штрих м ошибка нет связи",
      "count": 25
    },
    {
      "phrase": "штрих код м видео",
      "count": 25
    },
    {
      "phrase": "штрих м 2 другое состояние фн",
      "count": 25
    },
    {
      "phrase": "ожидание команды продолжения печати штрих м",
      "count": 24
    },
    {
      "phrase": "чек коррекции тест драйвер штрих м",
      "count": 24
    },
    {
      "phrase": "штрих м исчерпан ресурс",
      "count": 24
    },
    {
      "phrase": "штрих м проблемы",
      "count": 24
    },
    {
      "phrase": "штрих м заклинил",
      "count": 24
    },
    {
      "phrase": "штрих м установить дату",
      "count": 24
    },
    {
      "phrase": "штрих м 01ф тест драйвера",
      "count": 24
    },
    {
      "phrase": "штрих м документация",
      "count": 24
    },
    {
      "phrase": "ошибка 116 штрих м",
      "count": 24
    },
    {
      "phrase": "штрих м тест драйвера 5.17",
      "count": 24
    },
    {
      "phrase": "найти инструкцию к ккт ао штрих м",
      "count": 24
    },
    {
      "phrase": "штрих м производство",
      "count": 24
    },
    {
      "phrase": "штрих м ффд 1.2 прошивка",
      "count": 24
    },
    {
      "phrase": "продам штрих м",
      "count": 24
    },
    {
      "phrase": "как вставить карту в тахограф штрих м",
      "count": 24
    },
    {
      "phrase": "штрих м горячая линия",
      "count": 23
    },
    {
      "phrase": "кассовый аппарат штрих м ошибка 103",
      "count": 23
    },
    {
      "phrase": "ошибка е 103 кассовый аппарат штрих м",
      "count": 23
    },
    {
      "phrase": "штрих м последняя прошивка",
      "count": 23
    },
    {
      "phrase": "1с штрих м розничная",
      "count": 23
    },
    {
      "phrase": "штрих м 01ф отрезчик",
      "count": 23
    },
    {
      "phrase": "штрих м кассир 5 купить",
      "count": 23
    },
    {
      "phrase": "обновление кассы штрих м",
      "count": 23
    },
    {
      "phrase": "штрих м заводской номер",
      "count": 23
    },
    {
      "phrase": "обновить загрузчик штрих м",
      "count": 23
    },
    {
      "phrase": "драйвер штрих м 4.14",
      "count": 23
    },
    {
      "phrase": "обработка 1с штрих м",
      "count": 23
    },
    {
      "phrase": "штрих м wifi",
      "count": 23
    },
    {
      "phrase": "штрих м ошибка е 247",
      "count": 23
    },
    {
      "phrase": "штрих м 5.17 скачать",
      "count": 23
    },
    {
      "phrase": "штрих м драйвер 5.17 скачать",
      "count": 23
    },
    {
      "phrase": "программисты штрих м",
      "count": 23
    },
    {
      "phrase": "ооо штрих м инжиниринг",
      "count": 23
    },
    {
      "phrase": "штрих м регистратор подключение",
      "count": 23
    },
    {
      "phrase": "штрих м е 153",
      "count": 23
    },
    {
      "phrase": "штрих м прошивка 2025",
      "count": 23
    },
    {
      "phrase": "штрих м скачать бесплатно",
      "count": 23
    },
    {
      "phrase": "весы штрих м с печатью инструкция",
      "count": 23
    },
    {
      "phrase": "закрыт смена касса штрих м",
      "count": 22
    },
    {
      "phrase": "штрих м элвес фр ф",
      "count": 22
    },
    {
      "phrase": "штрих м отключить отрезчик в драйвере",
      "count": 22
    },
    {
      "phrase": "штрих м 1с 8",
      "count": 22
    },
    {
      "phrase": "программа 1с штрих м",
      "count": 22
    },
    {
      "phrase": "фискальник штрих м",
      "count": 22
    },
    {
      "phrase": "как проверить офд штрих м",
      "count": 22
    },
    {
      "phrase": "драйвер сканера штрих м",
      "count": 22
    },
    {
      "phrase": "штрих м нано",
      "count": 22
    },
    {
      "phrase": "штрих м компонента 1с",
      "count": 22
    },
    {
      "phrase": "драйвер штрих м таблицы",
      "count": 22
    },
    {
      "phrase": "штрих м разборка",
      "count": 22
    },
    {
      "phrase": "тд штрих м",
      "count": 22
    },
    {
      "phrase": "ошибка 119 ошибка лицензии штрих м",
      "count": 22
    },
    {
      "phrase": "штрих м подключение к офд",
      "count": 22
    },
    {
      "phrase": "тахограф штрих м видео",
      "count": 22
    },
    {
      "phrase": "ккм штрих м кассир",
      "count": 22
    },
    {
      "phrase": "касса штрих м как сделать возврат",
      "count": 21
    },
    {
      "phrase": "ошибка 88 штрих м",
      "count": 21
    },
    {
      "phrase": "штрих м пробить чек через драйвер",
      "count": 21
    },
    {
      "phrase": "тахограф штрих м питание",
      "count": 21
    },
    {
      "phrase": "штрих м не отправляет чеки",
      "count": 21
    },
    {
      "phrase": "цто штрих м",
      "count": 21
    },
    {
      "phrase": "технологическое обнуление штрих м",
      "count": 21
    },
    {
      "phrase": "штрих м фирма",
      "count": 21
    },
    {
      "phrase": "штрих м россия",
      "count": 21
    },
    {
      "phrase": "авито штрих м",
      "count": 21
    },
    {
      "phrase": "штрих м чек коррекции через тест драйвера",
      "count": 21
    },
    {
      "phrase": "настройка рндис штрих м",
      "count": 21
    },
    {
      "phrase": "штрих м исчерпан ресурс фн",
      "count": 21
    },
    {
      "phrase": "тахограф штрих м фото",
      "count": 21
    },
    {
      "phrase": "лицензия штрих м купить",
      "count": 21
    },
    {
      "phrase": "как правильно пользоваться тахографом штрих м",
      "count": 21
    },
    {
      "phrase": "как правильно пользоваться штрих м",
      "count": 21
    },
    {
      "phrase": "ошибка отрезчика штрих м",
      "count": 21
    },
    {
      "phrase": "тип суточного отчета штрих м",
      "count": 21
    },
    {
      "phrase": "116 ошибка озу штрих м",
      "count": 21
    },
    {
      "phrase": "как снять тахограф штрих м",
      "count": 20
    },
    {
      "phrase": "распечатка тахографа расшифровка штрих м",
      "count": 20
    },
    {
      "phrase": "штрих м через rndis",
      "count": 20
    },
    {
      "phrase": "штрих м е 244",
      "count": 20
    },
    {
      "phrase": "штрих м мигает красная лампочка",
      "count": 20
    },
    {
      "phrase": "весы штрих м 3",
      "count": 20
    },
    {
      "phrase": "возврат по кассе штрих м",
      "count": 20
    },
    {
      "phrase": "тахограф штрих м как пользоваться картой",
      "count": 20
    },
    {
      "phrase": "штрих м бу",
      "count": 20
    },
    {
      "phrase": "как включить тахограф штрих м",
      "count": 20
    },
    {
      "phrase": "штрих м не отправляет в офд",
      "count": 20
    },
    {
      "phrase": "создание чека коррекции для штрих м",
      "count": 20
    },
    {
      "phrase": "журавлев штрих м",
      "count": 20
    },
    {
      "phrase": "тахограф штрих м цена",
      "count": 20
    },
    {
      "phrase": "com порт занят другим приложением штрих м",
      "count": 20
    },
    {
      "phrase": "1с штрих м розничная торговля",
      "count": 20
    },
    {
      "phrase": "штрих м регистрация ккт",
      "count": 20
    },
    {
      "phrase": "торговое оборудование штрих м",
      "count": 20
    },
    {
      "phrase": "штрих м usb com",
      "count": 19
    },
    {
      "phrase": "касса штрих м сайт",
      "count": 19
    },
    {
      "phrase": "штрих м бухгалтерия",
      "count": 19
    },
    {
      "phrase": "штрих м после прошивки",
      "count": 19
    },
    {
      "phrase": "штрих м моргает красная лампочка",
      "count": 19
    },
    {
      "phrase": "сно штрих м",
      "count": 19
    },
    {
      "phrase": "штрих м ошибка е 153",
      "count": 19
    },
    {
      "phrase": "прошивка штрих м 22",
      "count": 19
    },
    {
      "phrase": "прошивки штрих м ндс 22",
      "count": 19
    },
    {
      "phrase": "штрих м ошибка 244",
      "count": 19
    },
    {
      "phrase": "штрих м напечатать чек",
      "count": 19
    },
    {
      "phrase": "штрих м установка времени",
      "count": 19
    },
    {
      "phrase": "куплю весы штрих м",
      "count": 19
    },
    {
      "phrase": "весы штрих принт м инструкция",
      "count": 19
    },
    {
      "phrase": "блок скзи тахографа штрих м",
      "count": 19
    },
    {
      "phrase": "штрих м алкоголь",
      "count": 19
    },
    {
      "phrase": "штрих м не отправляет чеки в офд",
      "count": 19
    },
    {
      "phrase": "штрих м аннулирует чек",
      "count": 19
    },
    {
      "phrase": "чеки штрих м программа",
      "count": 19
    },
    {
      "phrase": "штрих м переход на ффд 1.2",
      "count": 19
    },
    {
      "phrase": "штрих м 01 ф купить",
      "count": 19
    },
    {
      "phrase": "как прошить кассу штрих м",
      "count": 19
    },
    {
      "phrase": "кассовый аппарат штрих м инструкция по применению",
      "count": 19
    },
    {
      "phrase": "ккт штрих м документ не действителен",
      "count": 19
    },
    {
      "phrase": "весы штрих м с печатью этикеток настройка",
      "count": 18
    },
    {
      "phrase": "штрих м ру",
      "count": 18
    },
    {
      "phrase": "штрих м 02ф настройка",
      "count": 18
    },
    {
      "phrase": "программа касса штрих м",
      "count": 18
    },
    {
      "phrase": "актуальный драйвер штрих м",
      "count": 18
    },
    {
      "phrase": "сайт штрих м драйвер",
      "count": 18
    },
    {
      "phrase": "док штрих м",
      "count": 18
    },
    {
      "phrase": "1 нет связи штрих м",
      "count": 18
    },
    {
      "phrase": "подписка на лицензию штрих м",
      "count": 18
    },
    {
      "phrase": "ошибка 2 другое состояние фн штрих м",
      "count": 18
    },
    {
      "phrase": "штрих м ошибка другое состояние фн",
      "count": 18
    },
    {
      "phrase": "скачать 1с штрих м",
      "count": 18
    },
    {
      "phrase": "штрих м передать данные",
      "count": 18
    },
    {
      "phrase": "штрих м настройка подключения к офд",
      "count": 18
    },
    {
      "phrase": "проверка офд штрих м",
      "count": 18
    },
    {
      "phrase": "подключить штрих м к 1с",
      "count": 18
    },
    {
      "phrase": "штрих м драйвер 22",
      "count": 18
    },
    {
      "phrase": "штрих м москва",
      "count": 18
    },
    {
      "phrase": "штрих м горит красная лампочка",
      "count": 18
    },
    {
      "phrase": "штрих м ошибка е 244",
      "count": 18
    },
    {
      "phrase": "пароль штрих м принт",
      "count": 18
    },
    {
      "phrase": "тахограф штрих м как ввести пин код",
      "count": 18
    },
    {
      "phrase": "штрих м драйвер ккт 5",
      "count": 18
    },
    {
      "phrase": "штрих м отзывы",
      "count": 18
    },
    {
      "phrase": "штрих м qr код",
      "count": 17
    },
    {
      "phrase": "отмена чека штрих м",
      "count": 17
    },
    {
      "phrase": "штрих м спб",
      "count": 17
    },
    {
      "phrase": "узнать прошивку штрих м",
      "count": 17
    },
    {
      "phrase": "штрих м не открывается",
      "count": 17
    },
    {
      "phrase": "есм не видит кассу штрих м",
      "count": 17
    },
    {
      "phrase": "штрих м подключение через usb",
      "count": 17
    },
    {
      "phrase": "закрыть фискальный накопитель штрих м",
      "count": 17
    },
    {
      "phrase": "штрих м 5.19",
      "count": 17
    },
    {
      "phrase": "андрей журавлев штрих м",
      "count": 17
    },
    {
      "phrase": "штрих м услуги",
      "count": 17
    },
    {
      "phrase": "бумага для тахографа штрих м",
      "count": 17
    },
    {
      "phrase": "штрих м партнерам",
      "count": 17
    },
    {
      "phrase": "ошибка часов 121 в штрих м",
      "count": 17
    },
    {
      "phrase": "штрих м не включается",
      "count": 17
    },
    {
      "phrase": "прайс штрих м",
      "count": 17
    },
    {
      "phrase": "штрих принт м 15 2.5 драйвер",
      "count": 17
    },
    {
      "phrase": "пинг штрих м",
      "count": 17
    },
    {
      "phrase": "штрих м com драйвер",
      "count": 17
    },
    {
      "phrase": "штрих м кассир маркировка",
      "count": 17
    },
    {
      "phrase": "драйвер vcom штрих м скачать",
      "count": 17
    },
    {
      "phrase": "штрих м руководство программиста",
      "count": 17
    },
    {
      "phrase": "эквайринг штрих м",
      "count": 17
    },
    {
      "phrase": "8 connect timed out штрих м",
      "count": 17
    },
    {
      "phrase": "штрих м com порт недоступен",
      "count": 17
    },
    {
      "phrase": "штрих м рассинхронизация элементов нкм",
      "count": 17
    },
    {
      "phrase": "штрих м поменять бумагу",
      "count": 17
    },
    {
      "phrase": "пиот для штрих м 02ф",
      "count": 17
    },
    {
      "phrase": "как проверить связь штрих м",
      "count": 16
    },
    {
      "phrase": "как перезагрузить кассу штрих м",
      "count": 16
    },
    {
      "phrase": "штрих м помощь",
      "count": 16
    },
    {
      "phrase": "касса штрих м ошибки как исправить",
      "count": 16
    },
    {
      "phrase": "касса штрих м цена",
      "count": 16
    },
    {
      "phrase": "штрих м выбор",
      "count": 16
    },
    {
      "phrase": "штрих м настройка времени",
      "count": 16
    },
    {
      "phrase": "штрих м безналичными",
      "count": 16
    },
    {
      "phrase": "группа компаний штрих м",
      "count": 16
    },
    {
      "phrase": "утилита штрих м",
      "count": 16
    },
    {
      "phrase": "как подключить весы штрих м",
      "count": 16
    },
    {
      "phrase": "штрих м 01ф кто производитель",
      "count": 16
    },
    {
      "phrase": "замена фн штрих м 01ф инструкция",
      "count": 16
    },
    {
      "phrase": "штрих м настройка связи с офд",
      "count": 16
    },
    {
      "phrase": "аккорды эмма м штрих",
      "count": 16
    },
    {
      "phrase": "эмма м штрих коды аккорды",
      "count": 16
    },
    {
      "phrase": "драйвер штрих м 5.19",
      "count": 16
    },
    {
      "phrase": "мастер фискализации штрих м ффд 1.2",
      "count": 16
    },
    {
      "phrase": "штрих м система налогообложения",
      "count": 16
    },
    {
      "phrase": "установка тс пиот штрих м",
      "count": 16
    },
    {
      "phrase": "штрих м единая лицензия",
      "count": 16
    },
    {
      "phrase": "1с 8.3 штрих м",
      "count": 16
    },
    {
      "phrase": "как настроить время на тахографе штрих м",
      "count": 16
    },
    {
      "phrase": "ошибка 37h штрих м",
      "count": 16
    },
    {
      "phrase": "штрих м розничная торговля 5",
      "count": 16
    },
    {
      "phrase": "скачать обновление штрих м кассир",
      "count": 16
    },
    {
      "phrase": "скачать драйвер штрих м 5.18",
      "count": 16
    },
    {
      "phrase": "настройка офд штрих м rndis",
      "count": 16
    },
    {
      "phrase": "кассы штрих м официальный",
      "count": 16
    },
    {
      "phrase": "штрих м техническая поддержка",
      "count": 16
    },
    {
      "phrase": "штрих м замена ленты",
      "count": 16
    },
    {
      "phrase": "тест драйвера ккт штрих м 5.17",
      "count": 16
    },
    {
      "phrase": "штрих м 01ф таблицы",
      "count": 16
    },
    {
      "phrase": "принтер чеков штрих м",
      "count": 15
    },
    {
      "phrase": "сертификат штрих м",
      "count": 15
    },
    {
      "phrase": "весы штрих м 15 2.5 настройка",
      "count": 15
    },
    {
      "phrase": "teletype штрих м",
      "count": 15
    },
    {
      "phrase": "штрих м 01 замена фн",
      "count": 15
    },
    {
      "phrase": "выставить время штрих м",
      "count": 15
    },
    {
      "phrase": "штрих м taxo report",
      "count": 15
    },
    {
      "phrase": "штрих м какая лента",
      "count": 15
    },
    {
      "phrase": "штрих м сброс настроек",
      "count": 15
    },
    {
      "phrase": "штрих м база знаний",
      "count": 15
    },
    {
      "phrase": "штрих м официальный сайт драйвера",
      "count": 15
    },
    {
      "phrase": "штрих м 113 ошибка отрезчика",
      "count": 15
    },
    {
      "phrase": "маппинг штрих м",
      "count": 15
    },
    {
      "phrase": "прайс чекер штрих м",
      "count": 15
    },
    {
      "phrase": "производитель ккт штрих м",
      "count": 15
    },
    {
      "phrase": "цор штрих м",
      "count": 15
    },
    {
      "phrase": "ккм штрих м фр",
      "count": 15
    },
    {
      "phrase": "термоголовка штрих м 01ф",
      "count": 15
    },
    {
      "phrase": "штрих м некорректная операция 94",
      "count": 15
    },
    {
      "phrase": "штрих м драйвер windows 10",
      "count": 15
    },
    {
      "phrase": "ошибка 55 штрих м",
      "count": 15
    },
    {
      "phrase": "тахограф штрих м рассинхронизация элементов нкм",
      "count": 15
    },
    {
      "phrase": "штрих м вики",
      "count": 15
    },
    {
      "phrase": "штрих м драйвер rndis",
      "count": 15
    },
    {
      "phrase": "штрих м 33h",
      "count": 14
    },
    {
      "phrase": "штрих м микро к",
      "count": 14
    },
    {
      "phrase": "после активного отсутствия бумаги штрих м",
      "count": 14
    },
    {
      "phrase": "сетевой интерфейс штрих м",
      "count": 14
    },
    {
      "phrase": "весы штрих принт м статус ожидание",
      "count": 14
    },
    {
      "phrase": "ошибка штрих м 20",
      "count": 14
    },
    {
      "phrase": "как проверить связь с офд штрих м",
      "count": 14
    },
    {
      "phrase": "штрих м база данных",
      "count": 14
    },
    {
      "phrase": "авто штрих м",
      "count": 14
    },
    {
      "phrase": "штрих м выгрузка данных",
      "count": 14
    },
    {
      "phrase": "штрих м кассир мини пос",
      "count": 14
    },
    {
      "phrase": "внешняя компонента 1с штрих м",
      "count": 14
    },
    {
      "phrase": "закрытие чека штрих м",
      "count": 14
    },
    {
      "phrase": "штрих м драйвер ккт 5.19",
      "count": 14
    },
    {
      "phrase": "штрих м подключение по ethernet",
      "count": 14
    },
    {
      "phrase": "штрих м драйвер ккт 4.14",
      "count": 14
    },
    {
      "phrase": "штрих м acc lo",
      "count": 14
    },
    {
      "phrase": "перезагрузка штрих м через драйвер",
      "count": 14
    },
    {
      "phrase": "как прошить штрих м 02ф",
      "count": 14
    },
    {
      "phrase": "okassa штрих м",
      "count": 14
    },
    {
      "phrase": "элвес штрих м инструкция",
      "count": 13
    },
    {
      "phrase": "тахограф штрих м режим отдых",
      "count": 13
    },
    {
      "phrase": "как разобрать кассу штрих м",
      "count": 13
    },
    {
      "phrase": "комплект штрих м",
      "count": 13
    },
    {
      "phrase": "штрих м таблицы ккт",
      "count": 13
    },
    {
      "phrase": "чек коррекции онлайн касса штрих м",
      "count": 13
    },
    {
      "phrase": "штрих м касса выдает",
      "count": 13
    },
    {
      "phrase": "штрих м картинка",
      "count": 13
    },
    {
      "phrase": "штрих м банкротство",
      "count": 13
    },
    {
      "phrase": "весы штрих м настройка даты",
      "count": 13
    },
    {
      "phrase": "штрих м 5.1",
      "count": 13
    },
    {
      "phrase": "штрих м замена бумаги",
      "count": 13
    },
    {
      "phrase": "ошибка е153 штрих м",
      "count": 13
    },
    {
      "phrase": "штрих м е153",
      "count": 13
    },
    {
      "phrase": "ошибка 999 штрих м",
      "count": 13
    },
    {
      "phrase": "ккт штрих м 01ф как подключить",
      "count": 13
    },
    {
      "phrase": "штрих м превысило 24",
      "count": 13
    },
    {
      "phrase": "выгрузка данных тахограф штрих м",
      "count": 13
    },
    {
      "phrase": "штрих м автоматизация личный кабинет",
      "count": 13
    },
    {
      "phrase": "адаптер штрих м штрих фр к",
      "count": 13
    },
    {
      "phrase": "штрих м 01 ф замена фн",
      "count": 13
    },
    {
      "phrase": "регистратор выбытия штрих м инструкция",
      "count": 13
    },
    {
      "phrase": "мастер фискализации штрих м инструкция",
      "count": 13
    },
    {
      "phrase": "штрих м драйвер 64",
      "count": 13
    },
    {
      "phrase": "где найти регистрационный номер кассы штрих м",
      "count": 13
    },
    {
      "phrase": "скачать песню штрих коды эмма м",
      "count": 12
    },
    {
      "phrase": "штрих м перерегистрация без замены фн",
      "count": 12
    },
    {
      "phrase": "производитель кассы штрих м 01ф",
      "count": 12
    },
    {
      "phrase": "1с бухгалтерия штрих м",
      "count": 12
    },
    {
      "phrase": "штрих м транзакции",
      "count": 12
    },
    {
      "phrase": "термоголовка для весов штрих м",
      "count": 12
    },
    {
      "phrase": "штрих м личный кабинет цто",
      "count": 12
    },
    {
      "phrase": "кассы штрих м официальный сайт",
      "count": 12
    },
    {
      "phrase": "кассовый аппарат штрих м ошибка е244",
      "count": 12
    },
    {
      "phrase": "как отключить звук на тахографе штрих м",
      "count": 12
    },
    {
      "phrase": "штрих м настройка и подключение ккт",
      "count": 12
    },
    {
      "phrase": "штрих м 41",
      "count": 12
    },
    {
      "phrase": "как посмотреть версию прошивки штрих м",
      "count": 12
    },
    {
      "phrase": "сервер ккт штрих м",
      "count": 12
    },
    {
      "phrase": "ошибка 5eh штрих м",
      "count": 12
    },
    {
      "phrase": "штрих м кассир настройка тс пиот",
      "count": 12
    },
    {
      "phrase": "штрих м драйвер ккт 5.20",
      "count": 12
    },
    {
      "phrase": "как настроить rndis штрих м",
      "count": 12
    },
    {
      "phrase": "аспд штрих м ошибки",
      "count": 12
    },
    {
      "phrase": "штрих м терминал касса",
      "count": 12
    },
    {
      "phrase": "штрих м продуктовый магазин",
      "count": 12
    },
    {
      "phrase": "штрих м кассовый аппарат купить",
      "count": 12
    },
    {
      "phrase": "весы штрих м цена",
      "count": 12
    },
    {
      "phrase": "штрих м драйве",
      "count": 12
    },
    {
      "phrase": "как выключить тахограф штрих м",
      "count": 12
    },
    {
      "phrase": "штрих м организации",
      "count": 12
    },
    {
      "phrase": "как вынуть карту из тахографа штрих м",
      "count": 11
    },
    {
      "phrase": "прошивка штрих м под тс пилот",
      "count": 11
    },
    {
      "phrase": "штрих м смена превысила 24",
      "count": 11
    },
    {
      "phrase": "весы штрих м 15 2.5 инструкция",
      "count": 11
    },
    {
      "phrase": "касса штрих м возврат чека",
      "count": 11
    },
    {
      "phrase": "14h ограничение ресурса фн штрих м",
      "count": 11
    },
    {
      "phrase": "штрих м 14h",
      "count": 11
    },
    {
      "phrase": "как установить тахограф штрих м",
      "count": 11
    },
    {
      "phrase": "зао штрих м",
      "count": 11
    },
    {
      "phrase": "штрих м 01ф плата",
      "count": 11
    },
    {
      "phrase": "торговый баланс штрих м драйвер 1с",
      "count": 11
    },
    {
      "phrase": "штрих м 01ф цена",
      "count": 11
    },
    {
      "phrase": "штрих м тахомастер",
      "count": 11
    },
    {
      "phrase": "как закрыть смену штрих м через драйвер",
      "count": 11
    },
    {
      "phrase": "распиновка проводов на тахографе штрих м",
      "count": 11
    },
    {
      "phrase": "штрих м новости",
      "count": 11
    },
    {
      "phrase": "штрих принт м 15 2.5 д2и1 драйвер",
      "count": 11
    },
    {
      "phrase": "штрих м лайт драйвер",
      "count": 11
    },
    {
      "phrase": "штрих м on line",
      "count": 11
    },
    {
      "phrase": "штрих м не печатает x отчет",
      "count": 11
    },
    {
      "phrase": "1с штрих м розничная торговля 5.2",
      "count": 11
    },
    {
      "phrase": "скачать обновление штрих м кассир 5",
      "count": 11
    },
    {
      "phrase": "штрих м передать данные в офд",
      "count": 11
    },
    {
      "phrase": "фискальный накопитель штрих м 01ф",
      "count": 11
    },
    {
      "phrase": "штрих м оплата картой",
      "count": 11
    },
    {
      "phrase": "штрих м pos2",
      "count": 11
    },
    {
      "phrase": "штрих м ошибка 33h",
      "count": 11
    },
    {
      "phrase": "синхронизатор штрих м 5",
      "count": 11
    },
    {
      "phrase": "штрих м 7т",
      "count": 11
    },
    {
      "phrase": "облачная касса штрих м",
      "count": 11
    },
    {
      "phrase": "драйвер штрих м ндс 22",
      "count": 11
    },
    {
      "phrase": "тахограф штрих м дисплей",
      "count": 11
    },
    {
      "phrase": "как на тахографе штрих м удалить зуммер",
      "count": 11
    },
    {
      "phrase": "штрих м тахо report",
      "count": 11
    },
    {
      "phrase": "штрих принт м цена",
      "count": 11
    },
    {
      "phrase": "разбор штрих м",
      "count": 10
    },
    {
      "phrase": "штрих м 02 ф драйвер",
      "count": 10
    },
    {
      "phrase": "штрих м ошибка 9",
      "count": 10
    },
    {
      "phrase": "штрих м статус dhcp 6",
      "count": 10
    },
    {
      "phrase": "как работать с тахографом штрих м",
      "count": 10
    },
    {
      "phrase": "штрих м кассовые боксы",
      "count": 10
    },
    {
      "phrase": "режим ppp штрих м что это",
      "count": 10
    },
    {
      "phrase": "штрих м режим обмена с офд",
      "count": 10
    },
    {
      "phrase": "касса штрих м как сделать возврат чека",
      "count": 10
    },
    {
      "phrase": "как закрыть смену на кассе штрих м",
      "count": 10
    },
    {
      "phrase": "штрих м api",
      "count": 10
    },
    {
      "phrase": "как заменить бумагу в тахографе штрих м",
      "count": 10
    },
    {
      "phrase": "ожидание подтверждения ввода даты штрих м",
      "count": 10
    },
    {
      "phrase": "купить тахограф штрих м с блоком скзи",
      "count": 10
    },
    {
      "phrase": "проверка связи с офд штрих м",
      "count": 10
    },
    {
      "phrase": "штрих м обучение",
      "count": 10
    },
    {
      "phrase": "штрих м дисплей покупателя",
      "count": 10
    },
    {
      "phrase": "не отправляются чеки в офд штрих м",
      "count": 10
    },
    {
      "phrase": "ооо центр отраслевых решений штрих м",
      "count": 10
    },
    {
      "phrase": "драйвер rndis для штрих м windows 10",
      "count": 10
    },
    {
      "phrase": "штрих м драйвер ккт 5.18 скачать",
      "count": 10
    },
    {
      "phrase": "штрих м солюшен",
      "count": 10
    },
    {
      "phrase": "общество с ограниченной ответственностью штрих м инжиниринг",
      "count": 10
    },
    {
      "phrase": "как подключить кассу штрих м к компьютеру",
      "count": 10
    },
    {
      "phrase": "выплата штрих м",
      "count": 10
    },
    {
      "phrase": "разрешительный режим на кассах штрих м",
      "count": 10
    },
    {
      "phrase": "2 com порт недоступен штрих м",
      "count": 10
    },
    {
      "phrase": "настройка ккм штрих м",
      "count": 10
    },
    {
      "phrase": "скачать бесплатно эмма м штрихи",
      "count": 10
    },
    {
      "phrase": "эмма м штрих коды скачать бесплатно",
      "count": 10
    },
    {
      "phrase": "касса штрих м ошибка 244",
      "count": 10
    },
    {
      "phrase": "кассовый аппарат штрих м цена",
      "count": 10
    },
    {
      "phrase": "техподдержка штрих м круглосуточно",
      "count": 9
    },
    {
      "phrase": "штрих м настройка сети",
      "count": 9
    },
    {
      "phrase": "штрих м фр 01",
      "count": 9
    },
    {
      "phrase": "как вставить ленту в тахограф штрих м",
      "count": 9
    },
    {
      "phrase": "ремонт весов штрих м",
      "count": 9
    },
    {
      "phrase": "штрих м пей в режиме фр",
      "count": 9
    },
    {
      "phrase": "как открыть денежный ящик штрих м",
      "count": 9
    },
    {
      "phrase": "аспд штрих м 200 прошивка",
      "count": 9
    },
    {
      "phrase": "обозначение тахографа штрих м",
      "count": 9
    },
    {
      "phrase": "ошибка е 153 кассовый аппарат штрих м",
      "count": 9
    },
    {
      "phrase": "ккт штрих м 01ф купить",
      "count": 9
    },
    {
      "phrase": "е247 штрих м",
      "count": 9
    },
    {
      "phrase": "штрих м печатает построчно",
      "count": 9
    },
    {
      "phrase": "штрих м зебра",
      "count": 9
    },
    {
      "phrase": "смена превысила 24 часа штрих м",
      "count": 9
    },
    {
      "phrase": "внешняя компонента штрих м ккт 1с",
      "count": 9
    },
    {
      "phrase": "штрих м банкрот",
      "count": 9
    },
    {
      "phrase": "производитель стеллажей штрих м",
      "count": 9
    },
    {
      "phrase": "часовая зона штрих м",
      "count": 9
    },
    {
      "phrase": "штрих м неверное значение поля",
      "count": 9
    },
    {
      "phrase": "открытый документ продажа штрих м как закрыть",
      "count": 9
    },
    {
      "phrase": "штрих м драйвер ккт 5.21 1222",
      "count": 9
    },
    {
      "phrase": "штрих м как посмотреть ффд",
      "count": 9
    },
    {
      "phrase": "онлайн ккт штрих м",
      "count": 9
    },
    {
      "phrase": "штрих м весы дисплей",
      "count": 9
    },
    {
      "phrase": "штрих м копия чека",
      "count": 9
    },
    {
      "phrase": "штрих м 01ф разборка",
      "count": 9
    },
    {
      "phrase": "эмма м по штрих кодам переходов",
      "count": 9
    },
    {
      "phrase": "штрих м 13",
      "count": 9
    },
    {
      "phrase": "штрих м сайт производителя",
      "count": 9
    },
    {
      "phrase": "113 ошибка отрезчика штрих м как устранить",
      "count": 9
    },
    {
      "phrase": "штрих м 5 20",
      "count": 9
    },
    {
      "phrase": "как обновить штрих м кассир 5 инструкция",
      "count": 9
    },
    {
      "phrase": "штрих м прошивки пос центр",
      "count": 9
    },
    {
      "phrase": "программа штрих м розница",
      "count": 9
    },
    {
      "phrase": "логотип штрих м",
      "count": 9
    },
    {
      "phrase": "скачать штрих м rmk",
      "count": 9
    },
    {
      "phrase": "перезагрузить штрих м через драйвер",
      "count": 9
    },
    {
      "phrase": "эмма м штрих коды скачать бесплатно mp3",
      "count": 9
    },
    {
      "phrase": "штрих м официальный сайт техподдержка",
      "count": 9
    },
    {
      "phrase": "весы штрих м 7",
      "count": 9
    },
    {
      "phrase": "штрих м ошибки этикеток",
      "count": 9
    },
    {
      "phrase": "ввод недействительной карточки тахографа штрих м",
      "count": 9
    },
    {
      "phrase": "стеллаж металлический штрих м",
      "count": 8
    },
    {
      "phrase": "антенна для тахографа штрих м",
      "count": 8
    },
    {
      "phrase": "е 244 ошибка кассы штрих м",
      "count": 8
    },
    {
      "phrase": "касса штрих м ошибка е 247",
      "count": 8
    },
    {
      "phrase": "штрих м заклинила крышка",
      "count": 8
    },
    {
      "phrase": "штрих м настроить дату и время",
      "count": 8
    },
    {
      "phrase": "штрих м продолжить печать",
      "count": 8
    },
    {
      "phrase": "весы штрих принт м цена",
      "count": 8
    },
    {
      "phrase": "ошибка е40 штрих м",
      "count": 8
    },
    {
      "phrase": "штрих принт м купить",
      "count": 8
    },
    {
      "phrase": "штрих м кктлаб",
      "count": 8
    },
    {
      "phrase": "штрих м нож отрезчика мнет бумагу форум",
      "count": 8
    },
    {
      "phrase": "штрих м пей прошивка",
      "count": 8
    },
    {
      "phrase": "штрих м 01ф технологическое обнуление",
      "count": 8
    },
    {
      "phrase": "тест драйвера ккт штрих м 5.19",
      "count": 8
    },
    {
      "phrase": "штрих м обнулить",
      "count": 8
    },
    {
      "phrase": "прошивка тахографа штрих м",
      "count": 8
    },
    {
      "phrase": "штрих м 01ф запчасти",
      "count": 8
    },
    {
      "phrase": "отрезка чека штрих м таблицы настройка",
      "count": 8
    },
    {
      "phrase": "файл прошивки сп штрих м 02ф",
      "count": 8
    },
    {
      "phrase": "штрих м техобнуление",
      "count": 8
    },
    {
      "phrase": "штрих м ng",
      "count": 8
    },
    {
      "phrase": "сервер ас окп штрих м",
      "count": 8
    },
    {
      "phrase": "штрих м кассир 5 руководство администратора",
      "count": 8
    },
    {
      "phrase": "штрих м нск",
      "count": 8
    },
    {
      "phrase": "штрих м 02ф замена фн",
      "count": 8
    },
    {
      "phrase": "драйвер штрих м 01ф через usb vcom",
      "count": 8
    },
    {
      "phrase": "connection closed gracefully штрих м",
      "count": 8
    },
    {
      "phrase": "штрих м новый драйвер",
      "count": 8
    },
    {
      "phrase": "результат пинга 9 штрих м",
      "count": 8
    },
    {
      "phrase": "штрих м не открывается крышка",
      "count": 8
    },
    {
      "phrase": "е 153 ошибка кассы штрих м",
      "count": 8
    },
    {
      "phrase": "окдеск штрих м",
      "count": 8
    },
    {
      "phrase": "штрих м 1ф",
      "count": 8
    },
    {
      "phrase": "штрих м фрк",
      "count": 8
    },
    {
      "phrase": "закрыть смену фн штрих м",
      "count": 8
    },
    {
      "phrase": "kktlab штрих м",
      "count": 8
    },
    {
      "phrase": "распиновка тахографа штрих м подключение",
      "count": 8
    },
    {
      "phrase": "тест офд штрих м",
      "count": 8
    },
    {
      "phrase": "ао штрих м официальный сайт",
      "count": 8
    },
    {
      "phrase": "как пользоваться кассовым аппаратом штрих м",
      "count": 8
    },
    {
      "phrase": "штрих м определяется как новый rndis",
      "count": 7
    },
    {
      "phrase": "штрих м сити актуальная прошивка",
      "count": 7
    },
    {
      "phrase": "как заправить бумагу в тахограф штрих м",
      "count": 7
    },
    {
      "phrase": "моноблок штрих м обзор",
      "count": 7
    },
    {
      "phrase": "активация фн на штрих м",
      "count": 7
    },
    {
      "phrase": "штрих м тахограф обход",
      "count": 7
    },
    {
      "phrase": "котлета м картофельным пюре мираторг штрих код",
      "count": 7
    },
    {
      "phrase": "драже м м черная смородина штрих код",
      "count": 7
    },
    {
      "phrase": "весы штрих принт м ii 15 2.5",
      "count": 7
    },
    {
      "phrase": "касса штрих м как установить время",
      "count": 7
    },
    {
      "phrase": "штрих м кассир ошибка пиот",
      "count": 7
    },
    {
      "phrase": "закрытие аванса штрих м пример",
      "count": 7
    },
    {
      "phrase": "штрих м тахограф замена чека",
      "count": 7
    },
    {
      "phrase": "тахограф штрих м паспорт",
      "count": 7
    },
    {
      "phrase": "фискальный регистратор штрих м фр к",
      "count": 7
    },
    {
      "phrase": "шестеренки на штрих м элвес",
      "count": 7
    },
    {
      "phrase": "штрих м руководство пользователя",
      "count": 7
    },
    {
      "phrase": "по тс пиот для ккт штрих м",
      "count": 7
    },
    {
      "phrase": "штрих м драйвер ккт 5.17 скачать",
      "count": 7
    },
    {
      "phrase": "штрих м кассир 5 регламентные операции",
      "count": 7
    },
    {
      "phrase": "штрих м 01 ф тс пилот",
      "count": 7
    },
    {
      "phrase": "замена устройства модернизации в штрих м 02",
      "count": 7
    },
    {
      "phrase": "малая клавиатура для весов штрих принт м",
      "count": 7
    },
    {
      "phrase": "штрих м узнать ip",
      "count": 7
    },
    {
      "phrase": "штрих м меркурий",
      "count": 7
    },
    {
      "phrase": "штрих м кассир 5 или 1с рмк",
      "count": 7
    },
    {
      "phrase": "штрих коды эмма м где послушать",
      "count": 7
    },
    {
      "phrase": "rus формат фд 4 штрих м",
      "count": 6
    },
    {
      "phrase": "скачать тест драйвер штрих м 5.17",
      "count": 6
    },
    {
      "phrase": "штрих м кассир тспиот",
      "count": 6
    },
    {
      "phrase": "замена фискального накопителя штрих м 01ф",
      "count": 6
    },
    {
      "phrase": "ккт штрих м 01ф как включить dhcp",
      "count": 6
    },
    {
      "phrase": "штрих м рф",
      "count": 6
    },
    {
      "phrase": "ошибка передачи марки 94 штрих м",
      "count": 6
    },
    {
      "phrase": "весы штрих м годен до",
      "count": 6
    },
    {
      "phrase": "плата штрих м 01",
      "count": 6
    },
    {
      "phrase": "прошивка kktlab штрих м для ффд 1.2",
      "count": 6
    },
    {
      "phrase": "как заменить батарейку на штрих м",
      "count": 6
    },
    {
      "phrase": "ошибка е103 по кассе штрих м",
      "count": 6
    },
    {
      "phrase": "смена вида налогообложения штрих м мини",
      "count": 6
    },
    {
      "phrase": "штрих м 01ф крышка не плотно закрывается",
      "count": 6
    },
    {
      "phrase": "на кассе штрих м горит boot",
      "count": 6
    },
    {
      "phrase": "как разблокировать тахограф штрих м",
      "count": 6
    },
    {
      "phrase": "емей тахографа штрих м",
      "count": 6
    },
    {
      "phrase": "штрих коды эмма м кавер",
      "count": 6
    },
    {
      "phrase": "кассовый аппарат штрих м возврат",
      "count": 6
    },
    {
      "phrase": "торговые весы штрих м 6t 15 инструкция",
      "count": 6
    },
    {
      "phrase": "касса штрих м смартпос ф",
      "count": 6
    },
    {
      "phrase": "как выставить время на тахографе штрих м",
      "count": 6
    },
    {
      "phrase": "как снять тахограф штрих м с машины",
      "count": 6
    },
    {
      "phrase": "запчасти для тахографа штрих м",
      "count": 6
    },
    {
      "phrase": "код ошибки 0x32 штрих м",
      "count": 6
    },
    {
      "phrase": "тахограф штрих м характеристики",
      "count": 6
    },
    {
      "phrase": "совместимость пиот и штрих м проблемы",
      "count": 6
    },
    {
      "phrase": "штрих м фр к ремонт отрезчика форум",
      "count": 6
    },
    {
      "phrase": "аспд штрих м установка нового бнп",
      "count": 6
    },
    {
      "phrase": "штрих м таблица 17 региональные настройки",
      "count": 5
    },
    {
      "phrase": "как вытащить карту тахографа штрих м фото",
      "count": 5
    },
    {
      "phrase": "касса штрих м ошибка acc lo",
      "count": 5
    },
    {
      "phrase": "штрих м всегда печает итого",
      "count": 5
    },
    {
      "phrase": "инструкция по эксплуатации тахографа штрих м",
      "count": 5
    },
    {
      "phrase": "производитель кассы штрих м 02ф",
      "count": 5
    },
    {
      "phrase": "передача фио кассира в штрих м",
      "count": 5
    },
    {
      "phrase": "доработка до штрих м 02ф",
      "count": 5
    },
    {
      "phrase": "штрих м кассир 5 базовая версия скачать",
      "count": 5
    },
    {
      "phrase": "штрих м 02ф кто производитель",
      "count": 5
    },
    {
      "phrase": "авто штрих м официальный сайт",
      "count": 5
    },
    {
      "phrase": "штрих м снять с учета",
      "count": 5
    },
    {
      "phrase": "штрих м торговое предприятие 7 скачать",
      "count": 5
    },
    {
      "phrase": "штрих м лайт 01ф драйвер",
      "count": 5
    },
    {
      "phrase": "штрих м настройка wifi",
      "count": 5
    },
    {
      "phrase": "штрих м объект драйвера не установлен",
      "count": 5
    },
    {
      "phrase": "штрих м контакты",
      "count": 5
    },
    {
      "phrase": "программа штрих м розница как работать",
      "count": 5
    },
    {
      "phrase": "установка тахографа штрих м на shacman sx33186t366",
      "count": 5
    },
    {
      "phrase": "работа есп отключена штрих м",
      "count": 5
    },
    {
      "phrase": "не пропечатывается на весах штрих м",
      "count": 5
    },
    {
      "phrase": "ооо штрих м ставрополь",
      "count": 5
    },
    {
      "phrase": "штрих м настройка передача данных средствами драйвера",
      "count": 5
    },
    {
      "phrase": "аспд штрих м бнп ошибки",
      "count": 5
    },
    {
      "phrase": "замена бумаги в тахографе штрих м",
      "count": 5
    },
    {
      "phrase": "тахограф штрих м как установить время",
      "count": 5
    },
    {
      "phrase": "текст песни штрих коды эмма м",
      "count": 5
    },
    {
      "phrase": "фарш м свежесть говяжий штрих коды картинки",
      "count": 5
    },
    {
      "phrase": "штрих код м мс арахис 145",
      "count": 5
    },
    {
      "phrase": "драже м энд мс карамель штрих код",
      "count": 5
    },
    {
      "phrase": "абонентский терминал мобильное навигационное устройство штрих м",
      "count": 5
    },
    {
      "phrase": "даже м м черная смородина штрих код",
      "count": 5
    },
    {
      "phrase": "считать данные с тахографа штрих м",
      "count": 5
    },
    {
      "phrase": "превышено время ожидания ответа офд штрих м",
      "count": 5
    },
    {
      "phrase": "драйвер штрих м включение пиот",
      "count": 5
    },
    {
      "phrase": "кабель ком порт для штрих м",
      "count": 5
    },
    {
      "phrase": "как правильно поставить ленту тахографа штрих м",
      "count": 5
    },
    {
      "phrase": "эмма м штрих коды клип",
      "count": 5
    },
    {
      "phrase": "беспроводная зарядка для сканера штрих м",
      "count": 5
    },
    {
      "phrase": "ошибка е153 на кассе штрих м",
      "count": 5
    },
    {
      "phrase": "компания штрих м официальный сайт",
      "count": 5
    },
    {
      "phrase": "эмма м штрих коды караоке",
      "count": 3
    }
  ]
}
