{
  "seed": "облачная касса",
  "slug": "облачная-касса",
  "category": "entity",
  "cluster": "kkt",
  "fetchedAt": "2026-07-21T14:20:26.386Z",
  "count": 260,
  "phrases": [
    {
      "phrase": "облачная касса",
      "count": 11194
    },
    {
      "phrase": "облачная онлайн касса",
      "count": 1170
    },
    {
      "phrase": "облачная касса для ип",
      "count": 1047
    },
    {
      "phrase": "облачная касса атол",
      "count": 751
    },
    {
      "phrase": "чеки облачной кассы",
      "count": 671
    },
    {
      "phrase": "1с облачная касса",
      "count": 587
    },
    {
      "phrase": "аренда облачной кассы",
      "count": 447
    },
    {
      "phrase": "офд облачная касса",
      "count": 397
    },
    {
      "phrase": "облачная касса подключить",
      "count": 373
    },
    {
      "phrase": "альфа облачная касса",
      "count": 289
    },
    {
      "phrase": "облачная касса эвотор",
      "count": 274
    },
    {
      "phrase": "как работает облачная касса",
      "count": 269
    },
    {
      "phrase": "облачная интернет касса",
      "count": 256
    },
    {
      "phrase": "облачная касса альфа банк",
      "count": 255
    },
    {
      "phrase": "облачная касса для ооо",
      "count": 240
    },
    {
      "phrase": "облачная онлайн касса для ип",
      "count": 239
    },
    {
      "phrase": "фискальный накопитель для облачной кассы",
      "count": 205
    },
    {
      "phrase": "облачная касса точка",
      "count": 192
    },
    {
      "phrase": "облачная касса сбербанк",
      "count": 192
    },
    {
      "phrase": "облачная касса втб",
      "count": 185
    },
    {
      "phrase": "бизнес облачная касса",
      "count": 181
    },
    {
      "phrase": "ферма облачная касса",
      "count": 174
    },
    {
      "phrase": "т касса облачная",
      "count": 160
    },
    {
      "phrase": "облачная касса наличные",
      "count": 139
    },
    {
      "phrase": "облачная онлайн касса атол",
      "count": 135
    },
    {
      "phrase": "точка банк облачная касса",
      "count": 135
    },
    {
      "phrase": "облачная касса т банк",
      "count": 134
    },
    {
      "phrase": "услуги облачной кассы",
      "count": 126
    },
    {
      "phrase": "облачная касса билайн",
      "count": 125
    },
    {
      "phrase": "облачные кассы отзывы",
      "count": 120
    },
    {
      "phrase": "облачная касса юкасса",
      "count": 120
    },
    {
      "phrase": "бизнес ру облачная касса",
      "count": 119
    },
    {
      "phrase": "подключение облачной кассы",
      "count": 118
    },
    {
      "phrase": "облачная касса для ип на усн",
      "count": 116
    },
    {
      "phrase": "облачные кассы для магазина",
      "count": 116
    },
    {
      "phrase": "работа облачной кассы",
      "count": 109
    },
    {
      "phrase": "облачная касса кабинет",
      "count": 105
    },
    {
      "phrase": "облачный сервис касса",
      "count": 104
    },
    {
      "phrase": "облачная касса первый офд",
      "count": 104
    },
    {
      "phrase": "облачная касса стоимость",
      "count": 103
    },
    {
      "phrase": "облачная касса личный кабинет",
      "count": 99
    },
    {
      "phrase": "облачная касса ккт",
      "count": 98
    },
    {
      "phrase": "облачная касса купить",
      "count": 94
    },
    {
      "phrase": "облачная касса для интернет магазина",
      "count": 94
    },
    {
      "phrase": "облачная касса цена",
      "count": 93
    },
    {
      "phrase": "терминал облачной кассы",
      "count": 92
    },
    {
      "phrase": "облачная касса тарифы",
      "count": 89
    },
    {
      "phrase": "сколько стоит облачная касса",
      "count": 87
    },
    {
      "phrase": "аренда облачной кассы для ип",
      "count": 84
    },
    {
      "phrase": "офд ферма облачная касса",
      "count": 83
    },
    {
      "phrase": "облачная касса честный знак",
      "count": 81
    },
    {
      "phrase": "облачная касса paykeeper",
      "count": 79
    },
    {
      "phrase": "адрес облачной кассы",
      "count": 77
    },
    {
      "phrase": "регистрация облачной кассы",
      "count": 67
    },
    {
      "phrase": "лучшая облачная касса",
      "count": 64
    },
    {
      "phrase": "облачная касса тинькофф",
      "count": 64
    },
    {
      "phrase": "облачную касса настроить",
      "count": 62
    },
    {
      "phrase": "чек онлайн облачная касса",
      "count": 62
    },
    {
      "phrase": "облачной кассе нужен фискальный накопитель",
      "count": 62
    },
    {
      "phrase": "life pay облачная касса",
      "count": 61
    },
    {
      "phrase": "тс пиот для облачной кассы",
      "count": 61
    },
    {
      "phrase": "облачная касса оранж",
      "count": 60
    },
    {
      "phrase": "облачная касса сбербанк для ип",
      "count": 60
    },
    {
      "phrase": "облачная касса эватор",
      "count": 59
    },
    {
      "phrase": "аренда облачной онлайн кассы",
      "count": 59
    },
    {
      "phrase": "использование облачной кассы",
      "count": 57
    },
    {
      "phrase": "облачная касса фнс",
      "count": 57
    },
    {
      "phrase": "атолл облачная касса",
      "count": 55
    },
    {
      "phrase": "облачная онлайн касса для ооо",
      "count": 55
    },
    {
      "phrase": "облачные кассы ferma",
      "count": 55
    },
    {
      "phrase": "облачная касса втб для ип",
      "count": 54
    },
    {
      "phrase": "облачная касса orange data",
      "count": 53
    },
    {
      "phrase": "облачная касса для ип альфа банк",
      "count": 52
    },
    {
      "phrase": "выбрать облачную кассу",
      "count": 52
    },
    {
      "phrase": "облачная касса оранж дата",
      "count": 51
    },
    {
      "phrase": "облачная касса контур",
      "count": 49
    },
    {
      "phrase": "установить облачную кассу",
      "count": 48
    },
    {
      "phrase": "чек коррекции облачная касса",
      "count": 48
    },
    {
      "phrase": "рарус облачная касса",
      "count": 48
    },
    {
      "phrase": "облачная касса от банка",
      "count": 47
    },
    {
      "phrase": "облачная касса озон",
      "count": 47
    },
    {
      "phrase": "облачная касса настройка",
      "count": 46
    },
    {
      "phrase": "интернет эквайринг и облачная касса",
      "count": 46
    },
    {
      "phrase": "облачная касса с эквайрингом",
      "count": 46
    },
    {
      "phrase": "облачная касса для вендинга",
      "count": 46
    },
    {
      "phrase": "1с облачная касса атол",
      "count": 45
    },
    {
      "phrase": "1 офд облачная касса",
      "count": 45
    },
    {
      "phrase": "модуль касса облачная касса",
      "count": 45
    },
    {
      "phrase": "облачная касса 1с бухгалтерия",
      "count": 45
    },
    {
      "phrase": "1 с облачная касса",
      "count": 45
    },
    {
      "phrase": "облачная касса фискализация",
      "count": 44
    },
    {
      "phrase": "тбанк облачная касса",
      "count": 44
    },
    {
      "phrase": "смена облачной кассы",
      "count": 42
    },
    {
      "phrase": "сбис облачная касса",
      "count": 42
    },
    {
      "phrase": "облачная касса фн",
      "count": 41
    },
    {
      "phrase": "облачная касса интеграция с 1с",
      "count": 40
    },
    {
      "phrase": "зарегистрировать облачную кассу",
      "count": 40
    },
    {
      "phrase": "облачная касса яндекс",
      "count": 39
    },
    {
      "phrase": "аренда облачной кассы для ооо",
      "count": 39
    },
    {
      "phrase": "арендовать облачную кассу",
      "count": 39
    },
    {
      "phrase": "оформить облачную кассу",
      "count": 38
    },
    {
      "phrase": "1с рарус облачная касса",
      "count": 37
    },
    {
      "phrase": "облачная касса дешево",
      "count": 35
    },
    {
      "phrase": "digitalkassa облачная касса",
      "count": 34
    },
    {
      "phrase": "облачная касса розница",
      "count": 34
    },
    {
      "phrase": "штрих облачная касса",
      "count": 34
    },
    {
      "phrase": "вендиста облачная касса",
      "count": 34
    },
    {
      "phrase": "облачная касса без кассового аппарата",
      "count": 34
    },
    {
      "phrase": "открыть облачную кассу",
      "count": 33
    },
    {
      "phrase": "облачная касса бесплатно",
      "count": 33
    },
    {
      "phrase": "как пробить чек в облачной кассе",
      "count": 33
    },
    {
      "phrase": "ю касса облачная касса",
      "count": 33
    },
    {
      "phrase": "провайдер облачной кассы",
      "count": 32
    },
    {
      "phrase": "как сделать кассу облачной",
      "count": 32
    },
    {
      "phrase": "мобильная облачная касса",
      "count": 32
    },
    {
      "phrase": "облачная онлайн касса подключить",
      "count": 31
    },
    {
      "phrase": "облачная касса без фискального накопителя",
      "count": 31
    },
    {
      "phrase": "какие есть облачные кассы",
      "count": 31
    },
    {
      "phrase": "сколько стоит облачная касса для ип",
      "count": 30
    },
    {
      "phrase": "облачная касса для ип тинькофф",
      "count": 30
    },
    {
      "phrase": "облачные чеки без кассы",
      "count": 30
    },
    {
      "phrase": "облачная касса какую выбрать",
      "count": 30
    },
    {
      "phrase": "что значит облачная касса",
      "count": 29
    },
    {
      "phrase": "облачная касса и онлайн касса отличие",
      "count": 29
    },
    {
      "phrase": "атол облачные чеки облачная касса",
      "count": 29
    },
    {
      "phrase": "облачная касса для одного чека",
      "count": 29
    },
    {
      "phrase": "облачная касса для патента",
      "count": 28
    },
    {
      "phrase": "облачная касса cloudkassir",
      "count": 28
    },
    {
      "phrase": "облачная касса 54 фз",
      "count": 28
    },
    {
      "phrase": "нужен ли фискальный накопитель для облачной кассы",
      "count": 27
    },
    {
      "phrase": "облачная онлайн касса цена",
      "count": 27
    },
    {
      "phrase": "сбп облачная касса",
      "count": 27
    },
    {
      "phrase": "облачная касса место расчета",
      "count": 27
    },
    {
      "phrase": "инитпро облачная касса",
      "count": 26
    },
    {
      "phrase": "сбербизнес облачная касса",
      "count": 26
    },
    {
      "phrase": "для чего нужна облачная касса",
      "count": 26
    },
    {
      "phrase": "облачная касса рейтинг",
      "count": 26
    },
    {
      "phrase": "облачная касса эвотор для интернет магазина",
      "count": 26
    },
    {
      "phrase": "оператор облачных касс",
      "count": 26
    },
    {
      "phrase": "облачная касса для ип цена",
      "count": 25
    },
    {
      "phrase": "доставлен в облачную кассу",
      "count": 24
    },
    {
      "phrase": "клауд кассир облачная касса",
      "count": 24
    },
    {
      "phrase": "облачная касса на аусн",
      "count": 24
    },
    {
      "phrase": "облачная касса инструкция",
      "count": 24
    },
    {
      "phrase": "экватор облачная касса",
      "count": 23
    },
    {
      "phrase": "как закрыть облачную кассу",
      "count": 23
    },
    {
      "phrase": "пэй кипер облачная онлайн касса",
      "count": 23
    },
    {
      "phrase": "облачная касса на месяц",
      "count": 22
    },
    {
      "phrase": "облачная касса мой склад",
      "count": 22
    },
    {
      "phrase": "облачная касса сбербанк для ооо",
      "count": 22
    },
    {
      "phrase": "облачная онлайн касса сбербанк",
      "count": 22
    },
    {
      "phrase": "облачная касса оплата наличными",
      "count": 22
    },
    {
      "phrase": "облачная касса озон банк",
      "count": 22
    },
    {
      "phrase": "как подключить облачную кассу к 1с",
      "count": 22
    },
    {
      "phrase": "какая облачная касса лучше",
      "count": 22
    },
    {
      "phrase": "самые дешевые облачные кассы",
      "count": 21
    },
    {
      "phrase": "облачная онлайн касса стоимость",
      "count": 21
    },
    {
      "phrase": "облачные кассы для сайта",
      "count": 21
    },
    {
      "phrase": "офд ру облачная касса",
      "count": 21
    },
    {
      "phrase": "облачная касса aqsi",
      "count": 21
    },
    {
      "phrase": "1с касса облачное приложение",
      "count": 21
    },
    {
      "phrase": "диджитал облачная касса",
      "count": 21
    },
    {
      "phrase": "облачная касса решения",
      "count": 21
    },
    {
      "phrase": "билайн облачная касса личный кабинет",
      "count": 21
    },
    {
      "phrase": "как выглядит облачная касса",
      "count": 20
    },
    {
      "phrase": "подключить облачную кассу для ип",
      "count": 19
    },
    {
      "phrase": "облачная касса скачать",
      "count": 19
    },
    {
      "phrase": "чек не доставлен в облачную кассу",
      "count": 18
    },
    {
      "phrase": "чем отличается онлайн касса от облачной кассы",
      "count": 18
    },
    {
      "phrase": "облачная касса организации",
      "count": 18
    },
    {
      "phrase": "облачная касса атол интеграция с 1с",
      "count": 18
    },
    {
      "phrase": "подключение облачной кассы к 1с",
      "count": 18
    },
    {
      "phrase": "облачные кассы сравнение",
      "count": 18
    },
    {
      "phrase": "обычная касса облачная",
      "count": 18
    },
    {
      "phrase": "принцип работы облачной кассы",
      "count": 18
    },
    {
      "phrase": "бизнес ру облачная касса отзывы",
      "count": 17
    },
    {
      "phrase": "облачная онлайн касса 1с",
      "count": 17
    },
    {
      "phrase": "виды облачных касс",
      "count": 17
    },
    {
      "phrase": "облачная касса для ип на патенте",
      "count": 17
    },
    {
      "phrase": "атол облачная касса отзывы",
      "count": 16
    },
    {
      "phrase": "облачная касса комтет",
      "count": 16
    },
    {
      "phrase": "астрал облачная касса",
      "count": 16
    },
    {
      "phrase": "облачная касса на 1 чек",
      "count": 16
    },
    {
      "phrase": "облачная онлайн касса альфа банк",
      "count": 16
    },
    {
      "phrase": "стоимость облачной кассы для ип",
      "count": 15
    },
    {
      "phrase": "облачная касса без аренды",
      "count": 15
    },
    {
      "phrase": "облачная касса 1с унф",
      "count": 15
    },
    {
      "phrase": "как работает облачная онлайн касса",
      "count": 15
    },
    {
      "phrase": "облачная онлайн касса для ип цена",
      "count": 15
    },
    {
      "phrase": "тс пилот на облачной кассе",
      "count": 15
    },
    {
      "phrase": "облачная касса с поддержкой пиот",
      "count": 14
    },
    {
      "phrase": "облачная онлайн касса без кассового аппарата",
      "count": 14
    },
    {
      "phrase": "облачная касса под ключ",
      "count": 14
    },
    {
      "phrase": "сервис 1с облачная касса",
      "count": 13
    },
    {
      "phrase": "атол облачная касса как работает",
      "count": 13
    },
    {
      "phrase": "какую облачную кассу выбрать для ип",
      "count": 13
    },
    {
      "phrase": "как подключить облачную кассу к тс пиот",
      "count": 13
    },
    {
      "phrase": "такском облачная касса",
      "count": 13
    },
    {
      "phrase": "облачная касса без эквайринга",
      "count": 13
    },
    {
      "phrase": "облачная касса такси",
      "count": 12
    },
    {
      "phrase": "почековые облачные кассы",
      "count": 12
    },
    {
      "phrase": "облачная касса для турагентства",
      "count": 12
    },
    {
      "phrase": "портал облачных касс",
      "count": 12
    },
    {
      "phrase": "облачная касса ofd",
      "count": 12
    },
    {
      "phrase": "аренда облачной онлайн кассы для ип",
      "count": 12
    },
    {
      "phrase": "самые выгодные облачные кассы",
      "count": 11
    },
    {
      "phrase": "облачная касса от сбера",
      "count": 11
    },
    {
      "phrase": "облачная касса псб",
      "count": 11
    },
    {
      "phrase": "облачная касса контур офд",
      "count": 11
    },
    {
      "phrase": "аренда облачной кассы цена",
      "count": 11
    },
    {
      "phrase": "кто может применять облачную кассу",
      "count": 11
    },
    {
      "phrase": "облачная касса штрих м",
      "count": 11
    },
    {
      "phrase": "облачная касса прием наличных",
      "count": 11
    },
    {
      "phrase": "как снять с учета облачную кассу",
      "count": 10
    },
    {
      "phrase": "форум облачная касса",
      "count": 10
    },
    {
      "phrase": "облачная касса атол и тс пиот",
      "count": 10
    },
    {
      "phrase": "купить облачную онлайн кассу",
      "count": 10
    },
    {
      "phrase": "кит облачная касса",
      "count": 10
    },
    {
      "phrase": "облачная касса для ип точка банк",
      "count": 10
    },
    {
      "phrase": "робокасса облачная касса",
      "count": 10
    },
    {
      "phrase": "облачная касса ферма официальный сайт",
      "count": 10
    },
    {
      "phrase": "облачная касса для ип т банк",
      "count": 10
    },
    {
      "phrase": "облачная касса вти сервис",
      "count": 10
    },
    {
      "phrase": "как пользоваться облачной кассой",
      "count": 9
    },
    {
      "phrase": "для кого подходит облачная касса",
      "count": 9
    },
    {
      "phrase": "облачная касса для ооо на усн",
      "count": 9
    },
    {
      "phrase": "облачная касса для ип на аусн",
      "count": 9
    },
    {
      "phrase": "есп и облачная касса",
      "count": 9
    },
    {
      "phrase": "облачная касса для 1 чека",
      "count": 9
    },
    {
      "phrase": "облачная касса альфа банк для ооо",
      "count": 9
    },
    {
      "phrase": "регистрация облачной кассы в налоговой",
      "count": 9
    },
    {
      "phrase": "облачная касса платформа офд",
      "count": 9
    },
    {
      "phrase": "фискальный накопитель для облачной кассы купить",
      "count": 9
    },
    {
      "phrase": "схема работы облачная касса",
      "count": 9
    },
    {
      "phrase": "самая дешевая облачная касса для ип",
      "count": 8
    },
    {
      "phrase": "облачная касса 1с фреш",
      "count": 8
    },
    {
      "phrase": "сколько стоит облачная онлайн касса",
      "count": 8
    },
    {
      "phrase": "оранж дата облачная касса личный кабинет",
      "count": 7
    },
    {
      "phrase": "облачная касса разовая операция",
      "count": 7
    },
    {
      "phrase": "облачная онлайн касса для ип сбербанк",
      "count": 7
    },
    {
      "phrase": "атолл облачная касса для интернет магазина",
      "count": 7
    },
    {
      "phrase": "аренда облачной кассы альфа банк",
      "count": 7
    },
    {
      "phrase": "облачная касса курьеру в аренду",
      "count": 7
    },
    {
      "phrase": "нужно ли регистрировать облачную кассу в фнс",
      "count": 7
    },
    {
      "phrase": "топ облачных касс",
      "count": 7
    },
    {
      "phrase": "кто может использовать облачную кассу",
      "count": 6
    },
    {
      "phrase": "облачная касса почековый тариф",
      "count": 6
    },
    {
      "phrase": "облачная онлайн касса cloudkassir",
      "count": 6
    },
    {
      "phrase": "нужна ли облачная касса для интернет эквайринга",
      "count": 6
    },
    {
      "phrase": "облачная касса в эльбе",
      "count": 6
    },
    {
      "phrase": "терминалы и облачные кассы для вендинга",
      "count": 6
    },
    {
      "phrase": "orange data облачная касса отзывы",
      "count": 6
    },
    {
      "phrase": "как зарегистрировать облачную кассу в налоговой",
      "count": 6
    },
    {
      "phrase": "эвотор облачная касса тарифы",
      "count": 6
    },
    {
      "phrase": "рейтинг облачных касс для ип",
      "count": 5
    },
    {
      "phrase": "облачная касса лайф пэй",
      "count": 5
    },
    {
      "phrase": "облачные кассы первый ккм",
      "count": 5
    },
    {
      "phrase": "digitalkassa облачная касса вход",
      "count": 5
    },
    {
      "phrase": "облачная касса совкомбанк",
      "count": 5
    },
    {
      "phrase": "облачная онлайн касса для вендинга",
      "count": 3
    }
  ]
}
